public super class {
  version 51.0;
  name classref_0; // org/jasm/test/testclass/WideClass
  extends classref_2; // java/lang/Object
   //Constants
  const classref classref_0 utf8_1; // org/jasm/test/testclass/WideClass
  const utf8 utf8_1 "org/jasm/test/testclass/WideClass";
  const classref classref_2 utf8_3; // java/lang/Object
  const utf8 utf8_3 "java/lang/Object";
  const utf8 utf8_4 "<init>";
  const utf8 utf8_5 "()V";
  const utf8 utf8_6 "Code";
  const methodref methodref_7 classref_2, nameandtype_8; // class=java/lang/Object, name=<init>, descriptor=()V
  const nameandtype nameandtype_8 utf8_4, utf8_5; // name=<init> type=()V
  const utf8 utf8_9 "LineNumberTable";
  const utf8 utf8_10 "LocalVariableTable";
  const utf8 utf8_11 "this";
  const utf8 utf8_12 "Lorg/jasm/test/testclass/WideClass;";
  const utf8 utf8_13 "manyVariables";
  const double double_14 1.0p1; // 2.0
  const long long_16 4;
  const float float_18 1.8p2; // 6.0
  const double double_19 1.cp2; // 7.0
  const long long_21 9;
  const float float_23 1.6p3; // 11.0
  const double double_24 1.8p3; // 12.0
  const long long_26 14;
  const float float_28 1.0p4; // 16.0
  const double double_29 1.1p4; // 17.0
  const long long_31 19;
  const float float_33 1.5p4; // 21.0
  const double double_34 1.6p4; // 22.0
  const long long_36 24;
  const float float_38 1.ap4; // 26.0
  const double double_39 1.bp4; // 27.0
  const long long_41 29;
  const float float_43 1.fp4; // 31.0
  const double double_44 1.0p5; // 32.0
  const long long_46 34;
  const float float_48 1.2p5; // 36.0
  const double double_49 1.28p5; // 37.0
  const long long_51 39;
  const float float_53 1.48p5; // 41.0
  const double double_54 1.5p5; // 42.0
  const long long_56 44;
  const float float_58 1.7p5; // 46.0
  const double double_59 1.78p5; // 47.0
  const long long_61 49;
  const float float_63 1.98p5; // 51.0
  const double double_64 1.ap5; // 52.0
  const long long_66 54;
  const float float_68 1.cp5; // 56.0
  const double double_69 1.c8p5; // 57.0
  const long long_71 59;
  const float float_73 1.e8p5; // 61.0
  const double double_74 1.fp5; // 62.0
  const long long_76 64;
  const float float_78 1.08p6; // 66.0
  const double double_79 1.0cp6; // 67.0
  const long long_81 69;
  const float float_83 1.1cp6; // 71.0
  const double double_84 1.2p6; // 72.0
  const long long_86 74;
  const float float_88 1.3p6; // 76.0
  const double double_89 1.34p6; // 77.0
  const long long_91 79;
  const float float_93 1.44p6; // 81.0
  const double double_94 1.48p6; // 82.0
  const long long_96 84;
  const float float_98 1.58p6; // 86.0
  const double double_99 1.5cp6; // 87.0
  const long long_101 89;
  const float float_103 1.6cp6; // 91.0
  const double double_104 1.7p6; // 92.0
  const long long_106 94;
  const float float_108 1.8p6; // 96.0
  const double double_109 1.84p6; // 97.0
  const long long_111 99;
  const float float_113 1.94p6; // 101.0
  const double double_114 1.98p6; // 102.0
  const long long_116 104;
  const float float_118 1.a8p6; // 106.0
  const double double_119 1.acp6; // 107.0
  const long long_121 109;
  const float float_123 1.bcp6; // 111.0
  const double double_124 1.cp6; // 112.0
  const long long_126 114;
  const float float_128 1.dp6; // 116.0
  const double double_129 1.d4p6; // 117.0
  const long long_131 119;
  const float float_133 1.e4p6; // 121.0
  const double double_134 1.e8p6; // 122.0
  const long long_136 124;
  const float float_138 1.f8p6; // 126.0
  const double double_139 1.fcp6; // 127.0
  const long long_141 129;
  const float float_143 1.06p7; // 131.0
  const double double_144 1.08p7; // 132.0
  const long long_146 134;
  const float float_148 1.1p7; // 136.0
  const double double_149 1.12p7; // 137.0
  const long long_151 139;
  const float float_153 1.1ap7; // 141.0
  const double double_154 1.1cp7; // 142.0
  const long long_156 144;
  const float float_158 1.24p7; // 146.0
  const double double_159 1.26p7; // 147.0
  const long long_161 149;
  const float float_163 1.2ep7; // 151.0
  const double double_164 1.3p7; // 152.0
  const long long_166 154;
  const float float_168 1.38p7; // 156.0
  const double double_169 1.3ap7; // 157.0
  const long long_171 159;
  const float float_173 1.42p7; // 161.0
  const double double_174 1.44p7; // 162.0
  const long long_176 164;
  const float float_178 1.4cp7; // 166.0
  const double double_179 1.4ep7; // 167.0
  const long long_181 169;
  const float float_183 1.56p7; // 171.0
  const double double_184 1.58p7; // 172.0
  const long long_186 174;
  const float float_188 1.6p7; // 176.0
  const double double_189 1.62p7; // 177.0
  const long long_191 179;
  const float float_193 1.6ap7; // 181.0
  const double double_194 1.6cp7; // 182.0
  const long long_196 184;
  const float float_198 1.74p7; // 186.0
  const double double_199 1.76p7; // 187.0
  const long long_201 189;
  const float float_203 1.7ep7; // 191.0
  const double double_204 1.8p7; // 192.0
  const long long_206 194;
  const float float_208 1.88p7; // 196.0
  const double double_209 1.8ap7; // 197.0
  const long long_211 199;
  const float float_213 1.92p7; // 201.0
  const double double_214 1.94p7; // 202.0
  const long long_216 204;
  const float float_218 1.9cp7; // 206.0
  const double double_219 1.9ep7; // 207.0
  const long long_221 209;
  const float float_223 1.a6p7; // 211.0
  const double double_224 1.a8p7; // 212.0
  const long long_226 214;
  const float float_228 1.bp7; // 216.0
  const double double_229 1.b2p7; // 217.0
  const long long_231 219;
  const float float_233 1.bap7; // 221.0
  const double double_234 1.bcp7; // 222.0
  const long long_236 224;
  const float float_238 1.c4p7; // 226.0
  const double double_239 1.c6p7; // 227.0
  const long long_241 229;
  const float float_243 1.cep7; // 231.0
  const double double_244 1.dp7; // 232.0
  const long long_246 234;
  const float float_248 1.d8p7; // 236.0
  const double double_249 1.dap7; // 237.0
  const long long_251 239;
  const float float_253 1.e2p7; // 241.0
  const double double_254 1.e4p7; // 242.0
  const long long_256 244;
  const float float_258 1.ecp7; // 246.0
  const double double_259 1.eep7; // 247.0
  const long long_261 249;
  const float float_263 1.f6p7; // 251.0
  const double double_264 1.f8p7; // 252.0
  const long long_266 254;
  const float float_268 1.0p8; // 256.0
  const double double_269 1.01p8; // 257.0
  const long long_271 259;
  const float float_273 1.05p8; // 261.0
  const double double_274 1.06p8; // 262.0
  const long long_276 264;
  const float float_278 1.0ap8; // 266.0
  const double double_279 1.0bp8; // 267.0
  const long long_281 269;
  const float float_283 1.0fp8; // 271.0
  const double double_284 1.1p8; // 272.0
  const long long_286 274;
  const float float_288 1.14p8; // 276.0
  const double double_289 1.15p8; // 277.0
  const long long_291 279;
  const float float_293 1.19p8; // 281.0
  const double double_294 1.1ap8; // 282.0
  const long long_296 284;
  const float float_298 1.1ep8; // 286.0
  const double double_299 1.1fp8; // 287.0
  const long long_301 289;
  const float float_303 1.23p8; // 291.0
  const double double_304 1.24p8; // 292.0
  const long long_306 294;
  const float float_308 1.28p8; // 296.0
  const double double_309 1.29p8; // 297.0
  const long long_311 299;
  const classref classref_313 utf8_314; // java/lang/StringBuilder
  const utf8 utf8_314 "java/lang/StringBuilder";
  const methodref methodref_315 classref_313, nameandtype_8; // class=java/lang/StringBuilder, name=<init>, descriptor=()V
  const methodref methodref_316 classref_313, nameandtype_317; // class=java/lang/StringBuilder, name=append, descriptor=(Ljava/lang/Object;)Ljava/lang/StringBuilder;
  const nameandtype nameandtype_317 utf8_318, utf8_319; // name=append type=(Ljava/lang/Object;)Ljava/lang/StringBuilder;
  const utf8 utf8_318 "append";
  const utf8 utf8_319 "(Ljava/lang/Object;)Ljava/lang/StringBuilder;";
  const methodref methodref_320 classref_313, nameandtype_321; // class=java/lang/StringBuilder, name=append, descriptor=(F)Ljava/lang/StringBuilder;
  const nameandtype nameandtype_321 utf8_318, utf8_322; // name=append type=(F)Ljava/lang/StringBuilder;
  const utf8 utf8_322 "(F)Ljava/lang/StringBuilder;";
  const methodref methodref_323 classref_313, nameandtype_324; // class=java/lang/StringBuilder, name=append, descriptor=(D)Ljava/lang/StringBuilder;
  const nameandtype nameandtype_324 utf8_318, utf8_325; // name=append type=(D)Ljava/lang/StringBuilder;
  const utf8 utf8_325 "(D)Ljava/lang/StringBuilder;";
  const methodref methodref_326 classref_313, nameandtype_327; // class=java/lang/StringBuilder, name=append, descriptor=(I)Ljava/lang/StringBuilder;
  const nameandtype nameandtype_327 utf8_318, utf8_328; // name=append type=(I)Ljava/lang/StringBuilder;
  const utf8 utf8_328 "(I)Ljava/lang/StringBuilder;";
  const methodref methodref_329 classref_313, nameandtype_330; // class=java/lang/StringBuilder, name=append, descriptor=(J)Ljava/lang/StringBuilder;
  const nameandtype nameandtype_330 utf8_318, utf8_331; // name=append type=(J)Ljava/lang/StringBuilder;
  const utf8 utf8_331 "(J)Ljava/lang/StringBuilder;";
  const methodref methodref_332 classref_313, nameandtype_333; // class=java/lang/StringBuilder, name=toString, descriptor=()Ljava/lang/String;
  const nameandtype nameandtype_333 utf8_334, utf8_335; // name=toString type=()Ljava/lang/String;
  const utf8 utf8_334 "toString";
  const utf8 utf8_335 "()Ljava/lang/String;";
  const utf8 utf8_336 "o0";
  const utf8 utf8_337 "Ljava/lang/Object;";
  const utf8 utf8_338 "f1";
  const utf8 utf8_339 "F";
  const utf8 utf8_340 "d2";
  const utf8 utf8_341 "D";
  const utf8 utf8_342 "i3";
  const utf8 utf8_343 "I";
  const utf8 utf8_344 "l4";
  const utf8 utf8_345 "J";
  const utf8 utf8_346 "o5";
  const utf8 utf8_347 "f6";
  const utf8 utf8_348 "d7";
  const utf8 utf8_349 "i8";
  const utf8 utf8_350 "l9";
  const utf8 utf8_351 "o10";
  const utf8 utf8_352 "f11";
  const utf8 utf8_353 "d12";
  const utf8 utf8_354 "i13";
  const utf8 utf8_355 "l14";
  const utf8 utf8_356 "o15";
  const utf8 utf8_357 "f16";
  const utf8 utf8_358 "d17";
  const utf8 utf8_359 "i18";
  const utf8 utf8_360 "l19";
  const utf8 utf8_361 "o20";
  const utf8 utf8_362 "f21";
  const utf8 utf8_363 "d22";
  const utf8 utf8_364 "i23";
  const utf8 utf8_365 "l24";
  const utf8 utf8_366 "o25";
  const utf8 utf8_367 "f26";
  const utf8 utf8_368 "d27";
  const utf8 utf8_369 "i28";
  const utf8 utf8_370 "l29";
  const utf8 utf8_371 "o30";
  const utf8 utf8_372 "f31";
  const utf8 utf8_373 "d32";
  const utf8 utf8_374 "i33";
  const utf8 utf8_375 "l34";
  const utf8 utf8_376 "o35";
  const utf8 utf8_377 "f36";
  const utf8 utf8_378 "d37";
  const utf8 utf8_379 "i38";
  const utf8 utf8_380 "l39";
  const utf8 utf8_381 "o40";
  const utf8 utf8_382 "f41";
  const utf8 utf8_383 "d42";
  const utf8 utf8_384 "i43";
  const utf8 utf8_385 "l44";
  const utf8 utf8_386 "o45";
  const utf8 utf8_387 "f46";
  const utf8 utf8_388 "d47";
  const utf8 utf8_389 "i48";
  const utf8 utf8_390 "l49";
  const utf8 utf8_391 "o50";
  const utf8 utf8_392 "f51";
  const utf8 utf8_393 "d52";
  const utf8 utf8_394 "i53";
  const utf8 utf8_395 "l54";
  const utf8 utf8_396 "o55";
  const utf8 utf8_397 "f56";
  const utf8 utf8_398 "d57";
  const utf8 utf8_399 "i58";
  const utf8 utf8_400 "l59";
  const utf8 utf8_401 "o60";
  const utf8 utf8_402 "f61";
  const utf8 utf8_403 "d62";
  const utf8 utf8_404 "i63";
  const utf8 utf8_405 "l64";
  const utf8 utf8_406 "o65";
  const utf8 utf8_407 "f66";
  const utf8 utf8_408 "d67";
  const utf8 utf8_409 "i68";
  const utf8 utf8_410 "l69";
  const utf8 utf8_411 "o70";
  const utf8 utf8_412 "f71";
  const utf8 utf8_413 "d72";
  const utf8 utf8_414 "i73";
  const utf8 utf8_415 "l74";
  const utf8 utf8_416 "o75";
  const utf8 utf8_417 "f76";
  const utf8 utf8_418 "d77";
  const utf8 utf8_419 "i78";
  const utf8 utf8_420 "l79";
  const utf8 utf8_421 "o80";
  const utf8 utf8_422 "f81";
  const utf8 utf8_423 "d82";
  const utf8 utf8_424 "i83";
  const utf8 utf8_425 "l84";
  const utf8 utf8_426 "o85";
  const utf8 utf8_427 "f86";
  const utf8 utf8_428 "d87";
  const utf8 utf8_429 "i88";
  const utf8 utf8_430 "l89";
  const utf8 utf8_431 "o90";
  const utf8 utf8_432 "f91";
  const utf8 utf8_433 "d92";
  const utf8 utf8_434 "i93";
  const utf8 utf8_435 "l94";
  const utf8 utf8_436 "o95";
  const utf8 utf8_437 "f96";
  const utf8 utf8_438 "d97";
  const utf8 utf8_439 "i98";
  const utf8 utf8_440 "l99";
  const utf8 utf8_441 "o100";
  const utf8 utf8_442 "f101";
  const utf8 utf8_443 "d102";
  const utf8 utf8_444 "i103";
  const utf8 utf8_445 "l104";
  const utf8 utf8_446 "o105";
  const utf8 utf8_447 "f106";
  const utf8 utf8_448 "d107";
  const utf8 utf8_449 "i108";
  const utf8 utf8_450 "l109";
  const utf8 utf8_451 "o110";
  const utf8 utf8_452 "f111";
  const utf8 utf8_453 "d112";
  const utf8 utf8_454 "i113";
  const utf8 utf8_455 "l114";
  const utf8 utf8_456 "o115";
  const utf8 utf8_457 "f116";
  const utf8 utf8_458 "d117";
  const utf8 utf8_459 "i118";
  const utf8 utf8_460 "l119";
  const utf8 utf8_461 "o120";
  const utf8 utf8_462 "f121";
  const utf8 utf8_463 "d122";
  const utf8 utf8_464 "i123";
  const utf8 utf8_465 "l124";
  const utf8 utf8_466 "o125";
  const utf8 utf8_467 "f126";
  const utf8 utf8_468 "d127";
  const utf8 utf8_469 "i128";
  const utf8 utf8_470 "l129";
  const utf8 utf8_471 "o130";
  const utf8 utf8_472 "f131";
  const utf8 utf8_473 "d132";
  const utf8 utf8_474 "i133";
  const utf8 utf8_475 "l134";
  const utf8 utf8_476 "o135";
  const utf8 utf8_477 "f136";
  const utf8 utf8_478 "d137";
  const utf8 utf8_479 "i138";
  const utf8 utf8_480 "l139";
  const utf8 utf8_481 "o140";
  const utf8 utf8_482 "f141";
  const utf8 utf8_483 "d142";
  const utf8 utf8_484 "i143";
  const utf8 utf8_485 "l144";
  const utf8 utf8_486 "o145";
  const utf8 utf8_487 "f146";
  const utf8 utf8_488 "d147";
  const utf8 utf8_489 "i148";
  const utf8 utf8_490 "l149";
  const utf8 utf8_491 "o150";
  const utf8 utf8_492 "f151";
  const utf8 utf8_493 "d152";
  const utf8 utf8_494 "i153";
  const utf8 utf8_495 "l154";
  const utf8 utf8_496 "o155";
  const utf8 utf8_497 "f156";
  const utf8 utf8_498 "d157";
  const utf8 utf8_499 "i158";
  const utf8 utf8_500 "l159";
  const utf8 utf8_501 "o160";
  const utf8 utf8_502 "f161";
  const utf8 utf8_503 "d162";
  const utf8 utf8_504 "i163";
  const utf8 utf8_505 "l164";
  const utf8 utf8_506 "o165";
  const utf8 utf8_507 "f166";
  const utf8 utf8_508 "d167";
  const utf8 utf8_509 "i168";
  const utf8 utf8_510 "l169";
  const utf8 utf8_511 "o170";
  const utf8 utf8_512 "f171";
  const utf8 utf8_513 "d172";
  const utf8 utf8_514 "i173";
  const utf8 utf8_515 "l174";
  const utf8 utf8_516 "o175";
  const utf8 utf8_517 "f176";
  const utf8 utf8_518 "d177";
  const utf8 utf8_519 "i178";
  const utf8 utf8_520 "l179";
  const utf8 utf8_521 "o180";
  const utf8 utf8_522 "f181";
  const utf8 utf8_523 "d182";
  const utf8 utf8_524 "i183";
  const utf8 utf8_525 "l184";
  const utf8 utf8_526 "o185";
  const utf8 utf8_527 "f186";
  const utf8 utf8_528 "d187";
  const utf8 utf8_529 "i188";
  const utf8 utf8_530 "l189";
  const utf8 utf8_531 "o190";
  const utf8 utf8_532 "f191";
  const utf8 utf8_533 "d192";
  const utf8 utf8_534 "i193";
  const utf8 utf8_535 "l194";
  const utf8 utf8_536 "o195";
  const utf8 utf8_537 "f196";
  const utf8 utf8_538 "d197";
  const utf8 utf8_539 "i198";
  const utf8 utf8_540 "l199";
  const utf8 utf8_541 "o200";
  const utf8 utf8_542 "f201";
  const utf8 utf8_543 "d202";
  const utf8 utf8_544 "i203";
  const utf8 utf8_545 "l204";
  const utf8 utf8_546 "o205";
  const utf8 utf8_547 "f206";
  const utf8 utf8_548 "d207";
  const utf8 utf8_549 "i208";
  const utf8 utf8_550 "l209";
  const utf8 utf8_551 "o210";
  const utf8 utf8_552 "f211";
  const utf8 utf8_553 "d212";
  const utf8 utf8_554 "i213";
  const utf8 utf8_555 "l214";
  const utf8 utf8_556 "o215";
  const utf8 utf8_557 "f216";
  const utf8 utf8_558 "d217";
  const utf8 utf8_559 "i218";
  const utf8 utf8_560 "l219";
  const utf8 utf8_561 "o220";
  const utf8 utf8_562 "f221";
  const utf8 utf8_563 "d222";
  const utf8 utf8_564 "i223";
  const utf8 utf8_565 "l224";
  const utf8 utf8_566 "o225";
  const utf8 utf8_567 "f226";
  const utf8 utf8_568 "d227";
  const utf8 utf8_569 "i228";
  const utf8 utf8_570 "l229";
  const utf8 utf8_571 "o230";
  const utf8 utf8_572 "f231";
  const utf8 utf8_573 "d232";
  const utf8 utf8_574 "i233";
  const utf8 utf8_575 "l234";
  const utf8 utf8_576 "o235";
  const utf8 utf8_577 "f236";
  const utf8 utf8_578 "d237";
  const utf8 utf8_579 "i238";
  const utf8 utf8_580 "l239";
  const utf8 utf8_581 "o240";
  const utf8 utf8_582 "f241";
  const utf8 utf8_583 "d242";
  const utf8 utf8_584 "i243";
  const utf8 utf8_585 "l244";
  const utf8 utf8_586 "o245";
  const utf8 utf8_587 "f246";
  const utf8 utf8_588 "d247";
  const utf8 utf8_589 "i248";
  const utf8 utf8_590 "l249";
  const utf8 utf8_591 "o250";
  const utf8 utf8_592 "f251";
  const utf8 utf8_593 "d252";
  const utf8 utf8_594 "i253";
  const utf8 utf8_595 "l254";
  const utf8 utf8_596 "o255";
  const utf8 utf8_597 "f256";
  const utf8 utf8_598 "d257";
  const utf8 utf8_599 "i258";
  const utf8 utf8_600 "l259";
  const utf8 utf8_601 "o260";
  const utf8 utf8_602 "f261";
  const utf8 utf8_603 "d262";
  const utf8 utf8_604 "i263";
  const utf8 utf8_605 "l264";
  const utf8 utf8_606 "o265";
  const utf8 utf8_607 "f266";
  const utf8 utf8_608 "d267";
  const utf8 utf8_609 "i268";
  const utf8 utf8_610 "l269";
  const utf8 utf8_611 "o270";
  const utf8 utf8_612 "f271";
  const utf8 utf8_613 "d272";
  const utf8 utf8_614 "i273";
  const utf8 utf8_615 "l274";
  const utf8 utf8_616 "o275";
  const utf8 utf8_617 "f276";
  const utf8 utf8_618 "d277";
  const utf8 utf8_619 "i278";
  const utf8 utf8_620 "l279";
  const utf8 utf8_621 "o280";
  const utf8 utf8_622 "f281";
  const utf8 utf8_623 "d282";
  const utf8 utf8_624 "i283";
  const utf8 utf8_625 "l284";
  const utf8 utf8_626 "o285";
  const utf8 utf8_627 "f286";
  const utf8 utf8_628 "d287";
  const utf8 utf8_629 "i288";
  const utf8 utf8_630 "l289";
  const utf8 utf8_631 "o290";
  const utf8 utf8_632 "f291";
  const utf8 utf8_633 "d292";
  const utf8 utf8_634 "i293";
  const utf8 utf8_635 "l294";
  const utf8 utf8_636 "o295";
  const utf8 utf8_637 "f296";
  const utf8 utf8_638 "d297";
  const utf8 utf8_639 "i298";
  const utf8 utf8_640 "l299";
  const utf8 utf8_641 "sum";
  const utf8 utf8_642 "Ljava/lang/String;";
  const utf8 utf8_643 "main";
  const utf8 utf8_644 "([Ljava/lang/String;)V";
  const fieldref fieldref_645 classref_646, nameandtype_648; // class=java/lang/System, name=out, descriptor=Ljava/io/PrintStream;
  const classref classref_646 utf8_647; // java/lang/System
  const utf8 utf8_647 "java/lang/System";
  const nameandtype nameandtype_648 utf8_649, utf8_650; // name=out type=Ljava/io/PrintStream;
  const utf8 utf8_649 "out";
  const utf8 utf8_650 "Ljava/io/PrintStream;";
  const string string_651 utf8_652; // "Object o"
  const utf8 utf8_652 "Object o";
  const methodref methodref_653 classref_313, nameandtype_654; // class=java/lang/StringBuilder, name=<init>, descriptor=(Ljava/lang/String;)V
  const nameandtype nameandtype_654 utf8_4, utf8_655; // name=<init> type=(Ljava/lang/String;)V
  const utf8 utf8_655 "(Ljava/lang/String;)V";
  const string string_656 utf8_657; // "=null;"
  const utf8 utf8_657 "=null;";
  const methodref methodref_658 classref_313, nameandtype_659; // class=java/lang/StringBuilder, name=append, descriptor=(Ljava/lang/String;)Ljava/lang/StringBuilder;
  const nameandtype nameandtype_659 utf8_318, utf8_660; // name=append type=(Ljava/lang/String;)Ljava/lang/StringBuilder;
  const utf8 utf8_660 "(Ljava/lang/String;)Ljava/lang/StringBuilder;";
  const methodref methodref_661 classref_662, nameandtype_664; // class=java/io/PrintStream, name=println, descriptor=(Ljava/lang/String;)V
  const classref classref_662 utf8_663; // java/io/PrintStream
  const utf8 utf8_663 "java/io/PrintStream";
  const nameandtype nameandtype_664 utf8_665, utf8_655; // name=println type=(Ljava/lang/String;)V
  const utf8 utf8_665 "println";
  const string string_666 utf8_667; // "float f"
  const utf8 utf8_667 "float f";
  const string string_668 utf8_669; // "="
  const utf8 utf8_669 "=";
  const string string_670 utf8_671; // ".0f;"
  const utf8 utf8_671 ".0f;";
  const string string_672 utf8_673; // "double d"
  const utf8 utf8_673 "double d";
  const string string_674 utf8_675; // ".0;"
  const utf8 utf8_675 ".0;";
  const string string_676 utf8_677; // "int i"
  const utf8 utf8_677 "int i";
  const string string_678 utf8_679; // ";"
  const utf8 utf8_679 ";";
  const string string_680 utf8_681; // "long l"
  const utf8 utf8_681 "long l";
  const string string_682 utf8_683; // "String sum;"
  const utf8 utf8_683 "String sum;";
  const classref classref_684 utf8_685; // java/lang/StringBuffer
  const utf8 utf8_685 "java/lang/StringBuffer";
  const methodref methodref_686 classref_684, nameandtype_8; // class=java/lang/StringBuffer, name=<init>, descriptor=()V
  const string string_687 utf8_688; // "sum=\"\""
  const utf8 utf8_688 "sum=\"\"";
  const methodref methodref_689 classref_684, nameandtype_690; // class=java/lang/StringBuffer, name=append, descriptor=(Ljava/lang/String;)Ljava/lang/StringBuffer;
  const nameandtype nameandtype_690 utf8_318, utf8_691; // name=append type=(Ljava/lang/String;)Ljava/lang/StringBuffer;
  const utf8 utf8_691 "(Ljava/lang/String;)Ljava/lang/StringBuffer;";
  const string string_692 utf8_693; // "+"
  const utf8 utf8_693 "+";
  const string string_694 utf8_695; // "o"
  const utf8 utf8_695 "o";
  const string string_696 utf8_697; // "f"
  const utf8 utf8_697 "f";
  const string string_698 utf8_699; // "d"
  const utf8 utf8_699 "d";
  const string string_700 utf8_701; // "i"
  const utf8 utf8_701 "i";
  const string string_702 utf8_703; // "l"
  const utf8 utf8_703 "l";
  const methodref methodref_704 classref_684, nameandtype_333; // class=java/lang/StringBuffer, name=toString, descriptor=()Ljava/lang/String;
  const utf8 utf8_705 "args";
  const utf8 utf8_706 "[Ljava/lang/String;";
  const utf8 utf8_707 "buf";
  const utf8 utf8_708 "Ljava/lang/StringBuffer;";
  const utf8 utf8_709 "StackMapTable";
  const classref classref_710 utf8_706; // [Ljava/lang/String;
  const utf8 utf8_711 "SourceFile";
  const utf8 utf8_712 "WideClass.java";
  source file utf8_712; // WideClass.java
   //Fields
   //Methods
  public method {
    name utf8_4; // <init>
    descriptor utf8_5; // ()V
    line numbers {
      line ir0, 3;
    }
    debug vars {
      var a_0, ir0, utf8_11, utf8_12; // name=this,  descriptor=Lorg/jasm/test/testclass/WideClass;
    }
    maxstack 1;
    maxlocals 1;
    //Variables
    var object a_0;
    //Instructions
    ir0: aload a_0;
    invokespecial methodref_7; // class=java/lang/Object, name=<init>, descriptor=()V
    return;
  }
  public method {
    name utf8_13; // manyVariables
    descriptor utf8_5; // ()V
    line numbers {
      line ir0, 6;
      line ir2, 7;
      line ir4, 8;
      line ir8, 9;
      line ir11, 10;
      line ir16, 11;
      line ir19, 12;
      line ir23, 13;
      line ir28, 14;
      line ir32, 15;
      line ir37, 16;
      line ir40, 17;
      line ir44, 18;
      line ir49, 19;
      line ir53, 20;
      line ir58, 21;
      line ir61, 22;
      line ir65, 23;
      line ir70, 24;
      line ir74, 25;
      line ir79, 26;
      line ir82, 27;
      line ir86, 28;
      line ir91, 29;
      line ir95, 30;
      line ir100, 31;
      line ir103, 32;
      line ir107, 33;
      line ir112, 34;
      line ir116, 35;
      line ir121, 36;
      line ir124, 37;
      line ir128, 38;
      line ir133, 39;
      line ir137, 40;
      line ir142, 41;
      line ir145, 42;
      line ir149, 43;
      line ir154, 44;
      line ir158, 45;
      line ir163, 46;
      line ir166, 47;
      line ir170, 48;
      line ir175, 49;
      line ir179, 50;
      line ir184, 51;
      line ir187, 52;
      line ir191, 53;
      line ir196, 54;
      line ir200, 55;
      line ir205, 56;
      line ir208, 57;
      line ir212, 58;
      line ir217, 59;
      line ir221, 60;
      line ir226, 61;
      line ir229, 62;
      line ir233, 63;
      line ir238, 64;
      line ir242, 65;
      line ir247, 66;
      line ir250, 67;
      line ir254, 68;
      line ir259, 69;
      line ir263, 70;
      line ir268, 71;
      line ir271, 72;
      line ir275, 73;
      line ir280, 74;
      line ir284, 75;
      line ir289, 76;
      line ir292, 77;
      line ir296, 78;
      line ir301, 79;
      line ir305, 80;
      line ir310, 81;
      line ir313, 82;
      line ir317, 83;
      line ir322, 84;
      line ir326, 85;
      line ir331, 86;
      line ir334, 87;
      line ir338, 88;
      line ir343, 89;
      line ir347, 90;
      line ir352, 91;
      line ir355, 92;
      line ir359, 93;
      line ir364, 94;
      line ir368, 95;
      line ir373, 96;
      line ir376, 97;
      line ir380, 98;
      line ir385, 99;
      line ir389, 100;
      line ir394, 101;
      line ir397, 102;
      line ir401, 103;
      line ir406, 104;
      line ir410, 105;
      line ir415, 106;
      line ir418, 107;
      line ir422, 108;
      line ir427, 109;
      line ir431, 110;
      line ir436, 111;
      line ir439, 112;
      line ir443, 113;
      line ir448, 114;
      line ir452, 115;
      line ir457, 116;
      line ir460, 117;
      line ir464, 118;
      line ir469, 119;
      line ir473, 120;
      line ir478, 121;
      line ir481, 122;
      line ir485, 123;
      line ir490, 124;
      line ir494, 125;
      line ir499, 126;
      line ir502, 127;
      line ir506, 128;
      line ir511, 129;
      line ir515, 130;
      line ir520, 131;
      line ir523, 132;
      line ir527, 133;
      line ir532, 134;
      line ir537, 135;
      line ir542, 136;
      line ir545, 137;
      line ir549, 138;
      line ir554, 139;
      line ir559, 140;
      line ir564, 141;
      line ir567, 142;
      line ir571, 143;
      line ir576, 144;
      line ir581, 145;
      line ir586, 146;
      line ir589, 147;
      line ir593, 148;
      line ir598, 149;
      line ir603, 150;
      line ir608, 151;
      line ir611, 152;
      line ir615, 153;
      line ir620, 154;
      line ir625, 155;
      line ir630, 156;
      line ir633, 157;
      line ir637, 158;
      line ir642, 159;
      line ir647, 160;
      line ir652, 161;
      line ir655, 162;
      line ir659, 163;
      line ir664, 164;
      line ir669, 165;
      line ir674, 166;
      line ir677, 167;
      line ir681, 168;
      line ir686, 169;
      line ir691, 170;
      line ir696, 171;
      line ir699, 172;
      line ir703, 173;
      line ir708, 174;
      line ir713, 175;
      line ir718, 176;
      line ir721, 177;
      line ir725, 178;
      line ir730, 179;
      line ir735, 180;
      line ir740, 181;
      line ir743, 182;
      line ir747, 183;
      line ir752, 184;
      line ir757, 185;
      line ir762, 186;
      line ir765, 187;
      line ir769, 188;
      line ir774, 189;
      line ir781, 190;
      line ir788, 191;
      line ir793, 192;
      line ir799, 193;
      line ir806, 194;
      line ir813, 195;
      line ir820, 196;
      line ir825, 197;
      line ir831, 198;
      line ir838, 199;
      line ir845, 200;
      line ir852, 201;
      line ir857, 202;
      line ir863, 203;
      line ir870, 204;
      line ir877, 205;
      line ir884, 206;
      line ir889, 207;
      line ir895, 208;
      line ir902, 209;
      line ir909, 210;
      line ir916, 211;
      line ir921, 212;
      line ir927, 213;
      line ir934, 214;
      line ir941, 215;
      line ir948, 216;
      line ir953, 217;
      line ir959, 218;
      line ir966, 219;
      line ir973, 220;
      line ir980, 221;
      line ir985, 222;
      line ir991, 223;
      line ir998, 224;
      line ir1005, 225;
      line ir1012, 226;
      line ir1017, 227;
      line ir1023, 228;
      line ir1030, 229;
      line ir1037, 230;
      line ir1044, 231;
      line ir1049, 232;
      line ir1055, 233;
      line ir1062, 234;
      line ir1069, 235;
      line ir1076, 236;
      line ir1081, 237;
      line ir1087, 238;
      line ir1094, 239;
      line ir1101, 240;
      line ir1108, 241;
      line ir1113, 242;
      line ir1119, 243;
      line ir1126, 244;
      line ir1133, 245;
      line ir1140, 246;
      line ir1145, 247;
      line ir1151, 248;
      line ir1158, 249;
      line ir1165, 250;
      line ir1172, 251;
      line ir1177, 252;
      line ir1184, 253;
      line ir1191, 254;
      line ir1198, 255;
      line ir1205, 256;
      line ir1210, 257;
      line ir1217, 258;
      line ir1224, 259;
      line ir1231, 260;
      line ir1238, 261;
      line ir1243, 262;
      line ir1250, 263;
      line ir1257, 264;
      line ir1264, 265;
      line ir1271, 266;
      line ir1276, 267;
      line ir1283, 268;
      line ir1290, 269;
      line ir1297, 270;
      line ir1304, 271;
      line ir1309, 272;
      line ir1316, 273;
      line ir1323, 274;
      line ir1330, 275;
      line ir1337, 276;
      line ir1342, 277;
      line ir1349, 278;
      line ir1356, 279;
      line ir1363, 280;
      line ir1370, 281;
      line ir1375, 282;
      line ir1382, 283;
      line ir1389, 284;
      line ir1396, 285;
      line ir1403, 286;
      line ir1408, 287;
      line ir1415, 288;
      line ir1422, 289;
      line ir1429, 290;
      line ir1436, 291;
      line ir1441, 292;
      line ir1448, 293;
      line ir1455, 294;
      line ir1462, 295;
      line ir1469, 296;
      line ir1474, 297;
      line ir1481, 298;
      line ir1488, 299;
      line ir1495, 300;
      line ir1502, 301;
      line ir1507, 302;
      line ir1514, 303;
      line ir1521, 304;
      line ir1528, 305;
      line ir1535, 306;
      line ir1541, 308;
      line ir3286, 311;
    }
    debug vars {
      var a_0, ir0, utf8_11, utf8_12; // name=this,  descriptor=Lorg/jasm/test/testclass/WideClass;
      var a_1, ir2, utf8_336, utf8_337; // name=o0,  descriptor=Ljava/lang/Object;
      var f_2, ir4, utf8_338, utf8_339; // name=f1,  descriptor=F
      var d_3, ir8, utf8_340, utf8_341; // name=d2,  descriptor=D
      var i_5, ir11, utf8_342, utf8_343; // name=i3,  descriptor=I
      var l_6, ir16, utf8_344, utf8_345; // name=l4,  descriptor=J
      var a_8, ir19, utf8_346, utf8_337; // name=o5,  descriptor=Ljava/lang/Object;
      var f_9, ir23, utf8_347, utf8_339; // name=f6,  descriptor=F
      var d_10, ir28, utf8_348, utf8_341; // name=d7,  descriptor=D
      var i_12, ir32, utf8_349, utf8_343; // name=i8,  descriptor=I
      var l_13, ir37, utf8_350, utf8_345; // name=l9,  descriptor=J
      var a_15, ir40, utf8_351, utf8_337; // name=o10,  descriptor=Ljava/lang/Object;
      var f_16, ir44, utf8_352, utf8_339; // name=f11,  descriptor=F
      var d_17, ir49, utf8_353, utf8_341; // name=d12,  descriptor=D
      var i_19, ir53, utf8_354, utf8_343; // name=i13,  descriptor=I
      var l_20, ir58, utf8_355, utf8_345; // name=l14,  descriptor=J
      var a_22, ir61, utf8_356, utf8_337; // name=o15,  descriptor=Ljava/lang/Object;
      var f_23, ir65, utf8_357, utf8_339; // name=f16,  descriptor=F
      var d_24, ir70, utf8_358, utf8_341; // name=d17,  descriptor=D
      var i_26, ir74, utf8_359, utf8_343; // name=i18,  descriptor=I
      var l_27, ir79, utf8_360, utf8_345; // name=l19,  descriptor=J
      var a_29, ir82, utf8_361, utf8_337; // name=o20,  descriptor=Ljava/lang/Object;
      var f_30, ir86, utf8_362, utf8_339; // name=f21,  descriptor=F
      var d_31, ir91, utf8_363, utf8_341; // name=d22,  descriptor=D
      var i_33, ir95, utf8_364, utf8_343; // name=i23,  descriptor=I
      var l_34, ir100, utf8_365, utf8_345; // name=l24,  descriptor=J
      var a_36, ir103, utf8_366, utf8_337; // name=o25,  descriptor=Ljava/lang/Object;
      var f_37, ir107, utf8_367, utf8_339; // name=f26,  descriptor=F
      var d_38, ir112, utf8_368, utf8_341; // name=d27,  descriptor=D
      var i_40, ir116, utf8_369, utf8_343; // name=i28,  descriptor=I
      var l_41, ir121, utf8_370, utf8_345; // name=l29,  descriptor=J
      var a_43, ir124, utf8_371, utf8_337; // name=o30,  descriptor=Ljava/lang/Object;
      var f_44, ir128, utf8_372, utf8_339; // name=f31,  descriptor=F
      var d_45, ir133, utf8_373, utf8_341; // name=d32,  descriptor=D
      var i_47, ir137, utf8_374, utf8_343; // name=i33,  descriptor=I
      var l_48, ir142, utf8_375, utf8_345; // name=l34,  descriptor=J
      var a_50, ir145, utf8_376, utf8_337; // name=o35,  descriptor=Ljava/lang/Object;
      var f_51, ir149, utf8_377, utf8_339; // name=f36,  descriptor=F
      var d_52, ir154, utf8_378, utf8_341; // name=d37,  descriptor=D
      var i_54, ir158, utf8_379, utf8_343; // name=i38,  descriptor=I
      var l_55, ir163, utf8_380, utf8_345; // name=l39,  descriptor=J
      var a_57, ir166, utf8_381, utf8_337; // name=o40,  descriptor=Ljava/lang/Object;
      var f_58, ir170, utf8_382, utf8_339; // name=f41,  descriptor=F
      var d_59, ir175, utf8_383, utf8_341; // name=d42,  descriptor=D
      var i_61, ir179, utf8_384, utf8_343; // name=i43,  descriptor=I
      var l_62, ir184, utf8_385, utf8_345; // name=l44,  descriptor=J
      var a_64, ir187, utf8_386, utf8_337; // name=o45,  descriptor=Ljava/lang/Object;
      var f_65, ir191, utf8_387, utf8_339; // name=f46,  descriptor=F
      var d_66, ir196, utf8_388, utf8_341; // name=d47,  descriptor=D
      var i_68, ir200, utf8_389, utf8_343; // name=i48,  descriptor=I
      var l_69, ir205, utf8_390, utf8_345; // name=l49,  descriptor=J
      var a_71, ir208, utf8_391, utf8_337; // name=o50,  descriptor=Ljava/lang/Object;
      var f_72, ir212, utf8_392, utf8_339; // name=f51,  descriptor=F
      var d_73, ir217, utf8_393, utf8_341; // name=d52,  descriptor=D
      var i_75, ir221, utf8_394, utf8_343; // name=i53,  descriptor=I
      var l_76, ir226, utf8_395, utf8_345; // name=l54,  descriptor=J
      var a_78, ir229, utf8_396, utf8_337; // name=o55,  descriptor=Ljava/lang/Object;
      var f_79, ir233, utf8_397, utf8_339; // name=f56,  descriptor=F
      var d_80, ir238, utf8_398, utf8_341; // name=d57,  descriptor=D
      var i_82, ir242, utf8_399, utf8_343; // name=i58,  descriptor=I
      var l_83, ir247, utf8_400, utf8_345; // name=l59,  descriptor=J
      var a_85, ir250, utf8_401, utf8_337; // name=o60,  descriptor=Ljava/lang/Object;
      var f_86, ir254, utf8_402, utf8_339; // name=f61,  descriptor=F
      var d_87, ir259, utf8_403, utf8_341; // name=d62,  descriptor=D
      var i_89, ir263, utf8_404, utf8_343; // name=i63,  descriptor=I
      var l_90, ir268, utf8_405, utf8_345; // name=l64,  descriptor=J
      var a_92, ir271, utf8_406, utf8_337; // name=o65,  descriptor=Ljava/lang/Object;
      var f_93, ir275, utf8_407, utf8_339; // name=f66,  descriptor=F
      var d_94, ir280, utf8_408, utf8_341; // name=d67,  descriptor=D
      var i_96, ir284, utf8_409, utf8_343; // name=i68,  descriptor=I
      var l_97, ir289, utf8_410, utf8_345; // name=l69,  descriptor=J
      var a_99, ir292, utf8_411, utf8_337; // name=o70,  descriptor=Ljava/lang/Object;
      var f_100, ir296, utf8_412, utf8_339; // name=f71,  descriptor=F
      var d_101, ir301, utf8_413, utf8_341; // name=d72,  descriptor=D
      var i_103, ir305, utf8_414, utf8_343; // name=i73,  descriptor=I
      var l_104, ir310, utf8_415, utf8_345; // name=l74,  descriptor=J
      var a_106, ir313, utf8_416, utf8_337; // name=o75,  descriptor=Ljava/lang/Object;
      var f_107, ir317, utf8_417, utf8_339; // name=f76,  descriptor=F
      var d_108, ir322, utf8_418, utf8_341; // name=d77,  descriptor=D
      var i_110, ir326, utf8_419, utf8_343; // name=i78,  descriptor=I
      var l_111, ir331, utf8_420, utf8_345; // name=l79,  descriptor=J
      var a_113, ir334, utf8_421, utf8_337; // name=o80,  descriptor=Ljava/lang/Object;
      var f_114, ir338, utf8_422, utf8_339; // name=f81,  descriptor=F
      var d_115, ir343, utf8_423, utf8_341; // name=d82,  descriptor=D
      var i_117, ir347, utf8_424, utf8_343; // name=i83,  descriptor=I
      var l_118, ir352, utf8_425, utf8_345; // name=l84,  descriptor=J
      var a_120, ir355, utf8_426, utf8_337; // name=o85,  descriptor=Ljava/lang/Object;
      var f_121, ir359, utf8_427, utf8_339; // name=f86,  descriptor=F
      var d_122, ir364, utf8_428, utf8_341; // name=d87,  descriptor=D
      var i_124, ir368, utf8_429, utf8_343; // name=i88,  descriptor=I
      var l_125, ir373, utf8_430, utf8_345; // name=l89,  descriptor=J
      var a_127, ir376, utf8_431, utf8_337; // name=o90,  descriptor=Ljava/lang/Object;
      var f_128, ir380, utf8_432, utf8_339; // name=f91,  descriptor=F
      var d_129, ir385, utf8_433, utf8_341; // name=d92,  descriptor=D
      var i_131, ir389, utf8_434, utf8_343; // name=i93,  descriptor=I
      var l_132, ir394, utf8_435, utf8_345; // name=l94,  descriptor=J
      var a_134, ir397, utf8_436, utf8_337; // name=o95,  descriptor=Ljava/lang/Object;
      var f_135, ir401, utf8_437, utf8_339; // name=f96,  descriptor=F
      var d_136, ir406, utf8_438, utf8_341; // name=d97,  descriptor=D
      var i_138, ir410, utf8_439, utf8_343; // name=i98,  descriptor=I
      var l_139, ir415, utf8_440, utf8_345; // name=l99,  descriptor=J
      var a_141, ir418, utf8_441, utf8_337; // name=o100,  descriptor=Ljava/lang/Object;
      var f_142, ir422, utf8_442, utf8_339; // name=f101,  descriptor=F
      var d_143, ir427, utf8_443, utf8_341; // name=d102,  descriptor=D
      var i_145, ir431, utf8_444, utf8_343; // name=i103,  descriptor=I
      var l_146, ir436, utf8_445, utf8_345; // name=l104,  descriptor=J
      var a_148, ir439, utf8_446, utf8_337; // name=o105,  descriptor=Ljava/lang/Object;
      var f_149, ir443, utf8_447, utf8_339; // name=f106,  descriptor=F
      var d_150, ir448, utf8_448, utf8_341; // name=d107,  descriptor=D
      var i_152, ir452, utf8_449, utf8_343; // name=i108,  descriptor=I
      var l_153, ir457, utf8_450, utf8_345; // name=l109,  descriptor=J
      var a_155, ir460, utf8_451, utf8_337; // name=o110,  descriptor=Ljava/lang/Object;
      var f_156, ir464, utf8_452, utf8_339; // name=f111,  descriptor=F
      var d_157, ir469, utf8_453, utf8_341; // name=d112,  descriptor=D
      var i_159, ir473, utf8_454, utf8_343; // name=i113,  descriptor=I
      var l_160, ir478, utf8_455, utf8_345; // name=l114,  descriptor=J
      var a_162, ir481, utf8_456, utf8_337; // name=o115,  descriptor=Ljava/lang/Object;
      var f_163, ir485, utf8_457, utf8_339; // name=f116,  descriptor=F
      var d_164, ir490, utf8_458, utf8_341; // name=d117,  descriptor=D
      var i_166, ir494, utf8_459, utf8_343; // name=i118,  descriptor=I
      var l_167, ir499, utf8_460, utf8_345; // name=l119,  descriptor=J
      var a_169, ir502, utf8_461, utf8_337; // name=o120,  descriptor=Ljava/lang/Object;
      var f_170, ir506, utf8_462, utf8_339; // name=f121,  descriptor=F
      var d_171, ir511, utf8_463, utf8_341; // name=d122,  descriptor=D
      var i_173, ir515, utf8_464, utf8_343; // name=i123,  descriptor=I
      var l_174, ir520, utf8_465, utf8_345; // name=l124,  descriptor=J
      var a_176, ir523, utf8_466, utf8_337; // name=o125,  descriptor=Ljava/lang/Object;
      var f_177, ir527, utf8_467, utf8_339; // name=f126,  descriptor=F
      var d_178, ir532, utf8_468, utf8_341; // name=d127,  descriptor=D
      var i_180, ir537, utf8_469, utf8_343; // name=i128,  descriptor=I
      var l_181, ir542, utf8_470, utf8_345; // name=l129,  descriptor=J
      var a_183, ir545, utf8_471, utf8_337; // name=o130,  descriptor=Ljava/lang/Object;
      var f_184, ir549, utf8_472, utf8_339; // name=f131,  descriptor=F
      var d_185, ir554, utf8_473, utf8_341; // name=d132,  descriptor=D
      var i_187, ir559, utf8_474, utf8_343; // name=i133,  descriptor=I
      var l_188, ir564, utf8_475, utf8_345; // name=l134,  descriptor=J
      var a_190, ir567, utf8_476, utf8_337; // name=o135,  descriptor=Ljava/lang/Object;
      var f_191, ir571, utf8_477, utf8_339; // name=f136,  descriptor=F
      var d_192, ir576, utf8_478, utf8_341; // name=d137,  descriptor=D
      var i_194, ir581, utf8_479, utf8_343; // name=i138,  descriptor=I
      var l_195, ir586, utf8_480, utf8_345; // name=l139,  descriptor=J
      var a_197, ir589, utf8_481, utf8_337; // name=o140,  descriptor=Ljava/lang/Object;
      var f_198, ir593, utf8_482, utf8_339; // name=f141,  descriptor=F
      var d_199, ir598, utf8_483, utf8_341; // name=d142,  descriptor=D
      var i_201, ir603, utf8_484, utf8_343; // name=i143,  descriptor=I
      var l_202, ir608, utf8_485, utf8_345; // name=l144,  descriptor=J
      var a_204, ir611, utf8_486, utf8_337; // name=o145,  descriptor=Ljava/lang/Object;
      var f_205, ir615, utf8_487, utf8_339; // name=f146,  descriptor=F
      var d_206, ir620, utf8_488, utf8_341; // name=d147,  descriptor=D
      var i_208, ir625, utf8_489, utf8_343; // name=i148,  descriptor=I
      var l_209, ir630, utf8_490, utf8_345; // name=l149,  descriptor=J
      var a_211, ir633, utf8_491, utf8_337; // name=o150,  descriptor=Ljava/lang/Object;
      var f_212, ir637, utf8_492, utf8_339; // name=f151,  descriptor=F
      var d_213, ir642, utf8_493, utf8_341; // name=d152,  descriptor=D
      var i_215, ir647, utf8_494, utf8_343; // name=i153,  descriptor=I
      var l_216, ir652, utf8_495, utf8_345; // name=l154,  descriptor=J
      var a_218, ir655, utf8_496, utf8_337; // name=o155,  descriptor=Ljava/lang/Object;
      var f_219, ir659, utf8_497, utf8_339; // name=f156,  descriptor=F
      var d_220, ir664, utf8_498, utf8_341; // name=d157,  descriptor=D
      var i_222, ir669, utf8_499, utf8_343; // name=i158,  descriptor=I
      var l_223, ir674, utf8_500, utf8_345; // name=l159,  descriptor=J
      var a_225, ir677, utf8_501, utf8_337; // name=o160,  descriptor=Ljava/lang/Object;
      var f_226, ir681, utf8_502, utf8_339; // name=f161,  descriptor=F
      var d_227, ir686, utf8_503, utf8_341; // name=d162,  descriptor=D
      var i_229, ir691, utf8_504, utf8_343; // name=i163,  descriptor=I
      var l_230, ir696, utf8_505, utf8_345; // name=l164,  descriptor=J
      var a_232, ir699, utf8_506, utf8_337; // name=o165,  descriptor=Ljava/lang/Object;
      var f_233, ir703, utf8_507, utf8_339; // name=f166,  descriptor=F
      var d_234, ir708, utf8_508, utf8_341; // name=d167,  descriptor=D
      var i_236, ir713, utf8_509, utf8_343; // name=i168,  descriptor=I
      var l_237, ir718, utf8_510, utf8_345; // name=l169,  descriptor=J
      var a_239, ir721, utf8_511, utf8_337; // name=o170,  descriptor=Ljava/lang/Object;
      var f_240, ir725, utf8_512, utf8_339; // name=f171,  descriptor=F
      var d_241, ir730, utf8_513, utf8_341; // name=d172,  descriptor=D
      var i_243, ir735, utf8_514, utf8_343; // name=i173,  descriptor=I
      var l_244, ir740, utf8_515, utf8_345; // name=l174,  descriptor=J
      var a_246, ir743, utf8_516, utf8_337; // name=o175,  descriptor=Ljava/lang/Object;
      var f_247, ir747, utf8_517, utf8_339; // name=f176,  descriptor=F
      var d_248, ir752, utf8_518, utf8_341; // name=d177,  descriptor=D
      var i_250, ir757, utf8_519, utf8_343; // name=i178,  descriptor=I
      var l_251, ir762, utf8_520, utf8_345; // name=l179,  descriptor=J
      var a_253, ir765, utf8_521, utf8_337; // name=o180,  descriptor=Ljava/lang/Object;
      var f_254, ir769, utf8_522, utf8_339; // name=f181,  descriptor=F
      var d_255, ir774, utf8_523, utf8_341; // name=d182,  descriptor=D
      var i_257, ir781, utf8_524, utf8_343; // name=i183,  descriptor=I
      var l_258, ir788, utf8_525, utf8_345; // name=l184,  descriptor=J
      var a_260, ir793, utf8_526, utf8_337; // name=o185,  descriptor=Ljava/lang/Object;
      var f_261, ir799, utf8_527, utf8_339; // name=f186,  descriptor=F
      var d_262, ir806, utf8_528, utf8_341; // name=d187,  descriptor=D
      var i_264, ir813, utf8_529, utf8_343; // name=i188,  descriptor=I
      var l_265, ir820, utf8_530, utf8_345; // name=l189,  descriptor=J
      var a_267, ir825, utf8_531, utf8_337; // name=o190,  descriptor=Ljava/lang/Object;
      var f_268, ir831, utf8_532, utf8_339; // name=f191,  descriptor=F
      var d_269, ir838, utf8_533, utf8_341; // name=d192,  descriptor=D
      var i_271, ir845, utf8_534, utf8_343; // name=i193,  descriptor=I
      var l_272, ir852, utf8_535, utf8_345; // name=l194,  descriptor=J
      var a_274, ir857, utf8_536, utf8_337; // name=o195,  descriptor=Ljava/lang/Object;
      var f_275, ir863, utf8_537, utf8_339; // name=f196,  descriptor=F
      var d_276, ir870, utf8_538, utf8_341; // name=d197,  descriptor=D
      var i_278, ir877, utf8_539, utf8_343; // name=i198,  descriptor=I
      var l_279, ir884, utf8_540, utf8_345; // name=l199,  descriptor=J
      var a_281, ir889, utf8_541, utf8_337; // name=o200,  descriptor=Ljava/lang/Object;
      var f_282, ir895, utf8_542, utf8_339; // name=f201,  descriptor=F
      var d_283, ir902, utf8_543, utf8_341; // name=d202,  descriptor=D
      var i_285, ir909, utf8_544, utf8_343; // name=i203,  descriptor=I
      var l_286, ir916, utf8_545, utf8_345; // name=l204,  descriptor=J
      var a_288, ir921, utf8_546, utf8_337; // name=o205,  descriptor=Ljava/lang/Object;
      var f_289, ir927, utf8_547, utf8_339; // name=f206,  descriptor=F
      var d_290, ir934, utf8_548, utf8_341; // name=d207,  descriptor=D
      var i_292, ir941, utf8_549, utf8_343; // name=i208,  descriptor=I
      var l_293, ir948, utf8_550, utf8_345; // name=l209,  descriptor=J
      var a_295, ir953, utf8_551, utf8_337; // name=o210,  descriptor=Ljava/lang/Object;
      var f_296, ir959, utf8_552, utf8_339; // name=f211,  descriptor=F
      var d_297, ir966, utf8_553, utf8_341; // name=d212,  descriptor=D
      var i_299, ir973, utf8_554, utf8_343; // name=i213,  descriptor=I
      var l_300, ir980, utf8_555, utf8_345; // name=l214,  descriptor=J
      var a_302, ir985, utf8_556, utf8_337; // name=o215,  descriptor=Ljava/lang/Object;
      var f_303, ir991, utf8_557, utf8_339; // name=f216,  descriptor=F
      var d_304, ir998, utf8_558, utf8_341; // name=d217,  descriptor=D
      var i_306, ir1005, utf8_559, utf8_343; // name=i218,  descriptor=I
      var l_307, ir1012, utf8_560, utf8_345; // name=l219,  descriptor=J
      var a_309, ir1017, utf8_561, utf8_337; // name=o220,  descriptor=Ljava/lang/Object;
      var f_310, ir1023, utf8_562, utf8_339; // name=f221,  descriptor=F
      var d_311, ir1030, utf8_563, utf8_341; // name=d222,  descriptor=D
      var i_313, ir1037, utf8_564, utf8_343; // name=i223,  descriptor=I
      var l_314, ir1044, utf8_565, utf8_345; // name=l224,  descriptor=J
      var a_316, ir1049, utf8_566, utf8_337; // name=o225,  descriptor=Ljava/lang/Object;
      var f_317, ir1055, utf8_567, utf8_339; // name=f226,  descriptor=F
      var d_318, ir1062, utf8_568, utf8_341; // name=d227,  descriptor=D
      var i_320, ir1069, utf8_569, utf8_343; // name=i228,  descriptor=I
      var l_321, ir1076, utf8_570, utf8_345; // name=l229,  descriptor=J
      var a_323, ir1081, utf8_571, utf8_337; // name=o230,  descriptor=Ljava/lang/Object;
      var f_324, ir1087, utf8_572, utf8_339; // name=f231,  descriptor=F
      var d_325, ir1094, utf8_573, utf8_341; // name=d232,  descriptor=D
      var i_327, ir1101, utf8_574, utf8_343; // name=i233,  descriptor=I
      var l_328, ir1108, utf8_575, utf8_345; // name=l234,  descriptor=J
      var a_330, ir1113, utf8_576, utf8_337; // name=o235,  descriptor=Ljava/lang/Object;
      var f_331, ir1119, utf8_577, utf8_339; // name=f236,  descriptor=F
      var d_332, ir1126, utf8_578, utf8_341; // name=d237,  descriptor=D
      var i_334, ir1133, utf8_579, utf8_343; // name=i238,  descriptor=I
      var l_335, ir1140, utf8_580, utf8_345; // name=l239,  descriptor=J
      var a_337, ir1145, utf8_581, utf8_337; // name=o240,  descriptor=Ljava/lang/Object;
      var f_338, ir1151, utf8_582, utf8_339; // name=f241,  descriptor=F
      var d_339, ir1158, utf8_583, utf8_341; // name=d242,  descriptor=D
      var i_341, ir1165, utf8_584, utf8_343; // name=i243,  descriptor=I
      var l_342, ir1172, utf8_585, utf8_345; // name=l244,  descriptor=J
      var a_344, ir1177, utf8_586, utf8_337; // name=o245,  descriptor=Ljava/lang/Object;
      var f_345, ir1184, utf8_587, utf8_339; // name=f246,  descriptor=F
      var d_346, ir1191, utf8_588, utf8_341; // name=d247,  descriptor=D
      var i_348, ir1198, utf8_589, utf8_343; // name=i248,  descriptor=I
      var l_349, ir1205, utf8_590, utf8_345; // name=l249,  descriptor=J
      var a_351, ir1210, utf8_591, utf8_337; // name=o250,  descriptor=Ljava/lang/Object;
      var f_352, ir1217, utf8_592, utf8_339; // name=f251,  descriptor=F
      var d_353, ir1224, utf8_593, utf8_341; // name=d252,  descriptor=D
      var i_355, ir1231, utf8_594, utf8_343; // name=i253,  descriptor=I
      var l_356, ir1238, utf8_595, utf8_345; // name=l254,  descriptor=J
      var a_358, ir1243, utf8_596, utf8_337; // name=o255,  descriptor=Ljava/lang/Object;
      var f_359, ir1250, utf8_597, utf8_339; // name=f256,  descriptor=F
      var d_360, ir1257, utf8_598, utf8_341; // name=d257,  descriptor=D
      var i_362, ir1264, utf8_599, utf8_343; // name=i258,  descriptor=I
      var l_363, ir1271, utf8_600, utf8_345; // name=l259,  descriptor=J
      var a_365, ir1276, utf8_601, utf8_337; // name=o260,  descriptor=Ljava/lang/Object;
      var f_366, ir1283, utf8_602, utf8_339; // name=f261,  descriptor=F
      var d_367, ir1290, utf8_603, utf8_341; // name=d262,  descriptor=D
      var i_369, ir1297, utf8_604, utf8_343; // name=i263,  descriptor=I
      var l_370, ir1304, utf8_605, utf8_345; // name=l264,  descriptor=J
      var a_372, ir1309, utf8_606, utf8_337; // name=o265,  descriptor=Ljava/lang/Object;
      var f_373, ir1316, utf8_607, utf8_339; // name=f266,  descriptor=F
      var d_374, ir1323, utf8_608, utf8_341; // name=d267,  descriptor=D
      var i_376, ir1330, utf8_609, utf8_343; // name=i268,  descriptor=I
      var l_377, ir1337, utf8_610, utf8_345; // name=l269,  descriptor=J
      var a_379, ir1342, utf8_611, utf8_337; // name=o270,  descriptor=Ljava/lang/Object;
      var f_380, ir1349, utf8_612, utf8_339; // name=f271,  descriptor=F
      var d_381, ir1356, utf8_613, utf8_341; // name=d272,  descriptor=D
      var i_383, ir1363, utf8_614, utf8_343; // name=i273,  descriptor=I
      var l_384, ir1370, utf8_615, utf8_345; // name=l274,  descriptor=J
      var a_386, ir1375, utf8_616, utf8_337; // name=o275,  descriptor=Ljava/lang/Object;
      var f_387, ir1382, utf8_617, utf8_339; // name=f276,  descriptor=F
      var d_388, ir1389, utf8_618, utf8_341; // name=d277,  descriptor=D
      var i_390, ir1396, utf8_619, utf8_343; // name=i278,  descriptor=I
      var l_391, ir1403, utf8_620, utf8_345; // name=l279,  descriptor=J
      var a_393, ir1408, utf8_621, utf8_337; // name=o280,  descriptor=Ljava/lang/Object;
      var f_394, ir1415, utf8_622, utf8_339; // name=f281,  descriptor=F
      var d_395, ir1422, utf8_623, utf8_341; // name=d282,  descriptor=D
      var i_397, ir1429, utf8_624, utf8_343; // name=i283,  descriptor=I
      var l_398, ir1436, utf8_625, utf8_345; // name=l284,  descriptor=J
      var a_400, ir1441, utf8_626, utf8_337; // name=o285,  descriptor=Ljava/lang/Object;
      var f_401, ir1448, utf8_627, utf8_339; // name=f286,  descriptor=F
      var d_402, ir1455, utf8_628, utf8_341; // name=d287,  descriptor=D
      var i_404, ir1462, utf8_629, utf8_343; // name=i288,  descriptor=I
      var l_405, ir1469, utf8_630, utf8_345; // name=l289,  descriptor=J
      var a_407, ir1474, utf8_631, utf8_337; // name=o290,  descriptor=Ljava/lang/Object;
      var f_408, ir1481, utf8_632, utf8_339; // name=f291,  descriptor=F
      var d_409, ir1488, utf8_633, utf8_341; // name=d292,  descriptor=D
      var i_411, ir1495, utf8_634, utf8_343; // name=i293,  descriptor=I
      var l_412, ir1502, utf8_635, utf8_345; // name=l294,  descriptor=J
      var a_414, ir1507, utf8_636, utf8_337; // name=o295,  descriptor=Ljava/lang/Object;
      var f_415, ir1514, utf8_637, utf8_339; // name=f296,  descriptor=F
      var d_416, ir1521, utf8_638, utf8_341; // name=d297,  descriptor=D
      var i_418, ir1528, utf8_639, utf8_343; // name=i298,  descriptor=I
      var l_419, ir1535, utf8_640, utf8_345; // name=l299,  descriptor=J
      var a_421, ir3286, utf8_641, utf8_642; // name=sum,  descriptor=Ljava/lang/String;
    }
    maxstack 3;
    maxlocals 422;
    //Variables
    var object a_0;
    var object a_1;
    var float f_2;
    var double d_3;
    var int i_5;
    var long l_6;
    var object a_8;
    var float f_9;
    var double d_10;
    var int i_12;
    var long l_13;
    var object a_15;
    var float f_16;
    var double d_17;
    var int i_19;
    var long l_20;
    var object a_22;
    var float f_23;
    var double d_24;
    var int i_26;
    var long l_27;
    var object a_29;
    var float f_30;
    var double d_31;
    var int i_33;
    var long l_34;
    var object a_36;
    var float f_37;
    var double d_38;
    var int i_40;
    var long l_41;
    var object a_43;
    var float f_44;
    var double d_45;
    var int i_47;
    var long l_48;
    var object a_50;
    var float f_51;
    var double d_52;
    var int i_54;
    var long l_55;
    var object a_57;
    var float f_58;
    var double d_59;
    var int i_61;
    var long l_62;
    var object a_64;
    var float f_65;
    var double d_66;
    var int i_68;
    var long l_69;
    var object a_71;
    var float f_72;
    var double d_73;
    var int i_75;
    var long l_76;
    var object a_78;
    var float f_79;
    var double d_80;
    var int i_82;
    var long l_83;
    var object a_85;
    var float f_86;
    var double d_87;
    var int i_89;
    var long l_90;
    var object a_92;
    var float f_93;
    var double d_94;
    var int i_96;
    var long l_97;
    var object a_99;
    var float f_100;
    var double d_101;
    var int i_103;
    var long l_104;
    var object a_106;
    var float f_107;
    var double d_108;
    var int i_110;
    var long l_111;
    var object a_113;
    var float f_114;
    var double d_115;
    var int i_117;
    var long l_118;
    var object a_120;
    var float f_121;
    var double d_122;
    var int i_124;
    var long l_125;
    var object a_127;
    var float f_128;
    var double d_129;
    var int i_131;
    var long l_132;
    var object a_134;
    var float f_135;
    var double d_136;
    var int i_138;
    var long l_139;
    var object a_141;
    var float f_142;
    var double d_143;
    var int i_145;
    var long l_146;
    var object a_148;
    var float f_149;
    var double d_150;
    var int i_152;
    var long l_153;
    var object a_155;
    var float f_156;
    var double d_157;
    var int i_159;
    var long l_160;
    var object a_162;
    var float f_163;
    var double d_164;
    var int i_166;
    var long l_167;
    var object a_169;
    var float f_170;
    var double d_171;
    var int i_173;
    var long l_174;
    var object a_176;
    var float f_177;
    var double d_178;
    var int i_180;
    var long l_181;
    var object a_183;
    var float f_184;
    var double d_185;
    var int i_187;
    var long l_188;
    var object a_190;
    var float f_191;
    var double d_192;
    var int i_194;
    var long l_195;
    var object a_197;
    var float f_198;
    var double d_199;
    var int i_201;
    var long l_202;
    var object a_204;
    var float f_205;
    var double d_206;
    var int i_208;
    var long l_209;
    var object a_211;
    var float f_212;
    var double d_213;
    var int i_215;
    var long l_216;
    var object a_218;
    var float f_219;
    var double d_220;
    var int i_222;
    var long l_223;
    var object a_225;
    var float f_226;
    var double d_227;
    var int i_229;
    var long l_230;
    var object a_232;
    var float f_233;
    var double d_234;
    var int i_236;
    var long l_237;
    var object a_239;
    var float f_240;
    var double d_241;
    var int i_243;
    var long l_244;
    var object a_246;
    var float f_247;
    var double d_248;
    var int i_250;
    var long l_251;
    var object a_253;
    var float f_254;
    var double d_255;
    var int i_257;
    var long l_258;
    var object a_260;
    var float f_261;
    var double d_262;
    var int i_264;
    var long l_265;
    var object a_267;
    var float f_268;
    var double d_269;
    var int i_271;
    var long l_272;
    var object a_274;
    var float f_275;
    var double d_276;
    var int i_278;
    var long l_279;
    var object a_281;
    var float f_282;
    var double d_283;
    var int i_285;
    var long l_286;
    var object a_288;
    var float f_289;
    var double d_290;
    var int i_292;
    var long l_293;
    var object a_295;
    var float f_296;
    var double d_297;
    var int i_299;
    var long l_300;
    var object a_302;
    var float f_303;
    var double d_304;
    var int i_306;
    var long l_307;
    var object a_309;
    var float f_310;
    var double d_311;
    var int i_313;
    var long l_314;
    var object a_316;
    var float f_317;
    var double d_318;
    var int i_320;
    var long l_321;
    var object a_323;
    var float f_324;
    var double d_325;
    var int i_327;
    var long l_328;
    var object a_330;
    var float f_331;
    var double d_332;
    var int i_334;
    var long l_335;
    var object a_337;
    var float f_338;
    var double d_339;
    var int i_341;
    var long l_342;
    var object a_344;
    var float f_345;
    var double d_346;
    var int i_348;
    var long l_349;
    var object a_351;
    var float f_352;
    var double d_353;
    var int i_355;
    var long l_356;
    var object a_358;
    var float f_359;
    var double d_360;
    var int i_362;
    var long l_363;
    var object a_365;
    var float f_366;
    var double d_367;
    var int i_369;
    var long l_370;
    var object a_372;
    var float f_373;
    var double d_374;
    var int i_376;
    var long l_377;
    var object a_379;
    var float f_380;
    var double d_381;
    var int i_383;
    var long l_384;
    var object a_386;
    var float f_387;
    var double d_388;
    var int i_390;
    var long l_391;
    var object a_393;
    var float f_394;
    var double d_395;
    var int i_397;
    var long l_398;
    var object a_400;
    var float f_401;
    var double d_402;
    var int i_404;
    var long l_405;
    var object a_407;
    var float f_408;
    var double d_409;
    var int i_411;
    var long l_412;
    var object a_414;
    var float f_415;
    var double d_416;
    var int i_418;
    var long l_419;
    var object a_421;
    //Instructions
    ir0: aconst_null;
    astore a_1;
    ir2: fconst_1;
    fstore f_2;
    ir4: ldc2 double_14; // 2.0
    dstore d_3;
    ir8: iconst_3;
    istore i_5;
    ir11: ldc2 long_16;
    lstore l_6;
    ir16: aconst_null;
    astore a_8;
    ir19: ldc float_18; // 6.0
    fstore f_9;
    ir23: ldc2 double_19; // 7.0
    dstore d_10;
    ir28: bipush 8;
    istore i_12;
    ir32: ldc2 long_21;
    lstore l_13;
    ir37: aconst_null;
    astore a_15;
    ir40: ldc float_23; // 11.0
    fstore f_16;
    ir44: ldc2 double_24; // 12.0
    dstore d_17;
    ir49: bipush 13;
    istore i_19;
    ir53: ldc2 long_26;
    lstore l_20;
    ir58: aconst_null;
    astore a_22;
    ir61: ldc float_28; // 16.0
    fstore f_23;
    ir65: ldc2 double_29; // 17.0
    dstore d_24;
    ir70: bipush 18;
    istore i_26;
    ir74: ldc2 long_31;
    lstore l_27;
    ir79: aconst_null;
    astore a_29;
    ir82: ldc float_33; // 21.0
    fstore f_30;
    ir86: ldc2 double_34; // 22.0
    dstore d_31;
    ir91: bipush 23;
    istore i_33;
    ir95: ldc2 long_36;
    lstore l_34;
    ir100: aconst_null;
    astore a_36;
    ir103: ldc float_38; // 26.0
    fstore f_37;
    ir107: ldc2 double_39; // 27.0
    dstore d_38;
    ir112: bipush 28;
    istore i_40;
    ir116: ldc2 long_41;
    lstore l_41;
    ir121: aconst_null;
    astore a_43;
    ir124: ldc float_43; // 31.0
    fstore f_44;
    ir128: ldc2 double_44; // 32.0
    dstore d_45;
    ir133: bipush 33;
    istore i_47;
    ir137: ldc2 long_46;
    lstore l_48;
    ir142: aconst_null;
    astore a_50;
    ir145: ldc float_48; // 36.0
    fstore f_51;
    ir149: ldc2 double_49; // 37.0
    dstore d_52;
    ir154: bipush 38;
    istore i_54;
    ir158: ldc2 long_51;
    lstore l_55;
    ir163: aconst_null;
    astore a_57;
    ir166: ldc float_53; // 41.0
    fstore f_58;
    ir170: ldc2 double_54; // 42.0
    dstore d_59;
    ir175: bipush 43;
    istore i_61;
    ir179: ldc2 long_56;
    lstore l_62;
    ir184: aconst_null;
    astore a_64;
    ir187: ldc float_58; // 46.0
    fstore f_65;
    ir191: ldc2 double_59; // 47.0
    dstore d_66;
    ir196: bipush 48;
    istore i_68;
    ir200: ldc2 long_61;
    lstore l_69;
    ir205: aconst_null;
    astore a_71;
    ir208: ldc float_63; // 51.0
    fstore f_72;
    ir212: ldc2 double_64; // 52.0
    dstore d_73;
    ir217: bipush 53;
    istore i_75;
    ir221: ldc2 long_66;
    lstore l_76;
    ir226: aconst_null;
    astore a_78;
    ir229: ldc float_68; // 56.0
    fstore f_79;
    ir233: ldc2 double_69; // 57.0
    dstore d_80;
    ir238: bipush 58;
    istore i_82;
    ir242: ldc2 long_71;
    lstore l_83;
    ir247: aconst_null;
    astore a_85;
    ir250: ldc float_73; // 61.0
    fstore f_86;
    ir254: ldc2 double_74; // 62.0
    dstore d_87;
    ir259: bipush 63;
    istore i_89;
    ir263: ldc2 long_76;
    lstore l_90;
    ir268: aconst_null;
    astore a_92;
    ir271: ldc float_78; // 66.0
    fstore f_93;
    ir275: ldc2 double_79; // 67.0
    dstore d_94;
    ir280: bipush 68;
    istore i_96;
    ir284: ldc2 long_81;
    lstore l_97;
    ir289: aconst_null;
    astore a_99;
    ir292: ldc float_83; // 71.0
    fstore f_100;
    ir296: ldc2 double_84; // 72.0
    dstore d_101;
    ir301: bipush 73;
    istore i_103;
    ir305: ldc2 long_86;
    lstore l_104;
    ir310: aconst_null;
    astore a_106;
    ir313: ldc float_88; // 76.0
    fstore f_107;
    ir317: ldc2 double_89; // 77.0
    dstore d_108;
    ir322: bipush 78;
    istore i_110;
    ir326: ldc2 long_91;
    lstore l_111;
    ir331: aconst_null;
    astore a_113;
    ir334: ldc float_93; // 81.0
    fstore f_114;
    ir338: ldc2 double_94; // 82.0
    dstore d_115;
    ir343: bipush 83;
    istore i_117;
    ir347: ldc2 long_96;
    lstore l_118;
    ir352: aconst_null;
    astore a_120;
    ir355: ldc float_98; // 86.0
    fstore f_121;
    ir359: ldc2 double_99; // 87.0
    dstore d_122;
    ir364: bipush 88;
    istore i_124;
    ir368: ldc2 long_101;
    lstore l_125;
    ir373: aconst_null;
    astore a_127;
    ir376: ldc float_103; // 91.0
    fstore f_128;
    ir380: ldc2 double_104; // 92.0
    dstore d_129;
    ir385: bipush 93;
    istore i_131;
    ir389: ldc2 long_106;
    lstore l_132;
    ir394: aconst_null;
    astore a_134;
    ir397: ldc float_108; // 96.0
    fstore f_135;
    ir401: ldc2 double_109; // 97.0
    dstore d_136;
    ir406: bipush 98;
    istore i_138;
    ir410: ldc2 long_111;
    lstore l_139;
    ir415: aconst_null;
    astore a_141;
    ir418: ldc float_113; // 101.0
    fstore f_142;
    ir422: ldc2 double_114; // 102.0
    dstore d_143;
    ir427: bipush 103;
    istore i_145;
    ir431: ldc2 long_116;
    lstore l_146;
    ir436: aconst_null;
    astore a_148;
    ir439: ldc float_118; // 106.0
    fstore f_149;
    ir443: ldc2 double_119; // 107.0
    dstore d_150;
    ir448: bipush 108;
    istore i_152;
    ir452: ldc2 long_121;
    lstore l_153;
    ir457: aconst_null;
    astore a_155;
    ir460: ldc float_123; // 111.0
    fstore f_156;
    ir464: ldc2 double_124; // 112.0
    dstore d_157;
    ir469: bipush 113;
    istore i_159;
    ir473: ldc2 long_126;
    lstore l_160;
    ir478: aconst_null;
    astore a_162;
    ir481: ldc float_128; // 116.0
    fstore f_163;
    ir485: ldc2 double_129; // 117.0
    dstore d_164;
    ir490: bipush 118;
    istore i_166;
    ir494: ldc2 long_131;
    lstore l_167;
    ir499: aconst_null;
    astore a_169;
    ir502: ldc float_133; // 121.0
    fstore f_170;
    ir506: ldc2 double_134; // 122.0
    dstore d_171;
    ir511: bipush 123;
    istore i_173;
    ir515: ldc2 long_136;
    lstore l_174;
    ir520: aconst_null;
    astore a_176;
    ir523: ldc float_138; // 126.0
    fstore f_177;
    ir527: ldc2 double_139; // 127.0
    dstore d_178;
    ir532: sipush 128;
    istore i_180;
    ir537: ldc2 long_141;
    lstore l_181;
    ir542: aconst_null;
    astore a_183;
    ir545: ldc float_143; // 131.0
    fstore f_184;
    ir549: ldc2 double_144; // 132.0
    dstore d_185;
    ir554: sipush 133;
    istore i_187;
    ir559: ldc2 long_146;
    lstore l_188;
    ir564: aconst_null;
    astore a_190;
    ir567: ldc float_148; // 136.0
    fstore f_191;
    ir571: ldc2 double_149; // 137.0
    dstore d_192;
    ir576: sipush 138;
    istore i_194;
    ir581: ldc2 long_151;
    lstore l_195;
    ir586: aconst_null;
    astore a_197;
    ir589: ldc float_153; // 141.0
    fstore f_198;
    ir593: ldc2 double_154; // 142.0
    dstore d_199;
    ir598: sipush 143;
    istore i_201;
    ir603: ldc2 long_156;
    lstore l_202;
    ir608: aconst_null;
    astore a_204;
    ir611: ldc float_158; // 146.0
    fstore f_205;
    ir615: ldc2 double_159; // 147.0
    dstore d_206;
    ir620: sipush 148;
    istore i_208;
    ir625: ldc2 long_161;
    lstore l_209;
    ir630: aconst_null;
    astore a_211;
    ir633: ldc float_163; // 151.0
    fstore f_212;
    ir637: ldc2 double_164; // 152.0
    dstore d_213;
    ir642: sipush 153;
    istore i_215;
    ir647: ldc2 long_166;
    lstore l_216;
    ir652: aconst_null;
    astore a_218;
    ir655: ldc float_168; // 156.0
    fstore f_219;
    ir659: ldc2 double_169; // 157.0
    dstore d_220;
    ir664: sipush 158;
    istore i_222;
    ir669: ldc2 long_171;
    lstore l_223;
    ir674: aconst_null;
    astore a_225;
    ir677: ldc float_173; // 161.0
    fstore f_226;
    ir681: ldc2 double_174; // 162.0
    dstore d_227;
    ir686: sipush 163;
    istore i_229;
    ir691: ldc2 long_176;
    lstore l_230;
    ir696: aconst_null;
    astore a_232;
    ir699: ldc float_178; // 166.0
    fstore f_233;
    ir703: ldc2 double_179; // 167.0
    dstore d_234;
    ir708: sipush 168;
    istore i_236;
    ir713: ldc2 long_181;
    lstore l_237;
    ir718: aconst_null;
    astore a_239;
    ir721: ldc float_183; // 171.0
    fstore f_240;
    ir725: ldc2 double_184; // 172.0
    dstore d_241;
    ir730: sipush 173;
    istore i_243;
    ir735: ldc2 long_186;
    lstore l_244;
    ir740: aconst_null;
    astore a_246;
    ir743: ldc float_188; // 176.0
    fstore f_247;
    ir747: ldc2 double_189; // 177.0
    dstore d_248;
    ir752: sipush 178;
    istore i_250;
    ir757: ldc2 long_191;
    lstore l_251;
    ir762: aconst_null;
    astore a_253;
    ir765: ldc float_193; // 181.0
    fstore f_254;
    ir769: ldc2 double_194; // 182.0
    dstore d_255;
    ir774: sipush 183;
    wide istore i_257;
    ir781: ldc2 long_196;
    wide lstore l_258;
    ir788: aconst_null;
    wide astore a_260;
    ir793: ldc float_198; // 186.0
    wide fstore f_261;
    ir799: ldc2 double_199; // 187.0
    wide dstore d_262;
    ir806: sipush 188;
    wide istore i_264;
    ir813: ldc2 long_201;
    wide lstore l_265;
    ir820: aconst_null;
    wide astore a_267;
    ir825: ldc float_203; // 191.0
    wide fstore f_268;
    ir831: ldc2 double_204; // 192.0
    wide dstore d_269;
    ir838: sipush 193;
    wide istore i_271;
    ir845: ldc2 long_206;
    wide lstore l_272;
    ir852: aconst_null;
    wide astore a_274;
    ir857: ldc float_208; // 196.0
    wide fstore f_275;
    ir863: ldc2 double_209; // 197.0
    wide dstore d_276;
    ir870: sipush 198;
    wide istore i_278;
    ir877: ldc2 long_211;
    wide lstore l_279;
    ir884: aconst_null;
    wide astore a_281;
    ir889: ldc float_213; // 201.0
    wide fstore f_282;
    ir895: ldc2 double_214; // 202.0
    wide dstore d_283;
    ir902: sipush 203;
    wide istore i_285;
    ir909: ldc2 long_216;
    wide lstore l_286;
    ir916: aconst_null;
    wide astore a_288;
    ir921: ldc float_218; // 206.0
    wide fstore f_289;
    ir927: ldc2 double_219; // 207.0
    wide dstore d_290;
    ir934: sipush 208;
    wide istore i_292;
    ir941: ldc2 long_221;
    wide lstore l_293;
    ir948: aconst_null;
    wide astore a_295;
    ir953: ldc float_223; // 211.0
    wide fstore f_296;
    ir959: ldc2 double_224; // 212.0
    wide dstore d_297;
    ir966: sipush 213;
    wide istore i_299;
    ir973: ldc2 long_226;
    wide lstore l_300;
    ir980: aconst_null;
    wide astore a_302;
    ir985: ldc float_228; // 216.0
    wide fstore f_303;
    ir991: ldc2 double_229; // 217.0
    wide dstore d_304;
    ir998: sipush 218;
    wide istore i_306;
    ir1005: ldc2 long_231;
    wide lstore l_307;
    ir1012: aconst_null;
    wide astore a_309;
    ir1017: ldc float_233; // 221.0
    wide fstore f_310;
    ir1023: ldc2 double_234; // 222.0
    wide dstore d_311;
    ir1030: sipush 223;
    wide istore i_313;
    ir1037: ldc2 long_236;
    wide lstore l_314;
    ir1044: aconst_null;
    wide astore a_316;
    ir1049: ldc float_238; // 226.0
    wide fstore f_317;
    ir1055: ldc2 double_239; // 227.0
    wide dstore d_318;
    ir1062: sipush 228;
    wide istore i_320;
    ir1069: ldc2 long_241;
    wide lstore l_321;
    ir1076: aconst_null;
    wide astore a_323;
    ir1081: ldc float_243; // 231.0
    wide fstore f_324;
    ir1087: ldc2 double_244; // 232.0
    wide dstore d_325;
    ir1094: sipush 233;
    wide istore i_327;
    ir1101: ldc2 long_246;
    wide lstore l_328;
    ir1108: aconst_null;
    wide astore a_330;
    ir1113: ldc float_248; // 236.0
    wide fstore f_331;
    ir1119: ldc2 double_249; // 237.0
    wide dstore d_332;
    ir1126: sipush 238;
    wide istore i_334;
    ir1133: ldc2 long_251;
    wide lstore l_335;
    ir1140: aconst_null;
    wide astore a_337;
    ir1145: ldc float_253; // 241.0
    wide fstore f_338;
    ir1151: ldc2 double_254; // 242.0
    wide dstore d_339;
    ir1158: sipush 243;
    wide istore i_341;
    ir1165: ldc2 long_256;
    wide lstore l_342;
    ir1172: aconst_null;
    wide astore a_344;
    ir1177: ldc float_258; // 246.0
    wide fstore f_345;
    ir1184: ldc2 double_259; // 247.0
    wide dstore d_346;
    ir1191: sipush 248;
    wide istore i_348;
    ir1198: ldc2 long_261;
    wide lstore l_349;
    ir1205: aconst_null;
    wide astore a_351;
    ir1210: ldc float_263; // 251.0
    wide fstore f_352;
    ir1217: ldc2 double_264; // 252.0
    wide dstore d_353;
    ir1224: sipush 253;
    wide istore i_355;
    ir1231: ldc2 long_266;
    wide lstore l_356;
    ir1238: aconst_null;
    wide astore a_358;
    ir1243: ldc float_268; // 256.0
    wide fstore f_359;
    ir1250: ldc2 double_269; // 257.0
    wide dstore d_360;
    ir1257: sipush 258;
    wide istore i_362;
    ir1264: ldc2 long_271;
    wide lstore l_363;
    ir1271: aconst_null;
    wide astore a_365;
    ir1276: ldc float_273; // 261.0
    wide fstore f_366;
    ir1283: ldc2 double_274; // 262.0
    wide dstore d_367;
    ir1290: sipush 263;
    wide istore i_369;
    ir1297: ldc2 long_276;
    wide lstore l_370;
    ir1304: aconst_null;
    wide astore a_372;
    ir1309: ldc float_278; // 266.0
    wide fstore f_373;
    ir1316: ldc2 double_279; // 267.0
    wide dstore d_374;
    ir1323: sipush 268;
    wide istore i_376;
    ir1330: ldc2 long_281;
    wide lstore l_377;
    ir1337: aconst_null;
    wide astore a_379;
    ir1342: ldc float_283; // 271.0
    wide fstore f_380;
    ir1349: ldc2 double_284; // 272.0
    wide dstore d_381;
    ir1356: sipush 273;
    wide istore i_383;
    ir1363: ldc2 long_286;
    wide lstore l_384;
    ir1370: aconst_null;
    wide astore a_386;
    ir1375: ldc float_288; // 276.0
    wide fstore f_387;
    ir1382: ldc2 double_289; // 277.0
    wide dstore d_388;
    ir1389: sipush 278;
    wide istore i_390;
    ir1396: ldc2 long_291;
    wide lstore l_391;
    ir1403: aconst_null;
    wide astore a_393;
    ir1408: ldc float_293; // 281.0
    wide fstore f_394;
    ir1415: ldc2 double_294; // 282.0
    wide dstore d_395;
    ir1422: sipush 283;
    wide istore i_397;
    ir1429: ldc2 long_296;
    wide lstore l_398;
    ir1436: aconst_null;
    wide astore a_400;
    ir1441: ldc float_298; // 286.0
    wide fstore f_401;
    ir1448: ldc2 double_299; // 287.0
    wide dstore d_402;
    ir1455: sipush 288;
    wide istore i_404;
    ir1462: ldc2 long_301;
    wide lstore l_405;
    ir1469: aconst_null;
    wide astore a_407;
    ir1474: ldc float_303; // 291.0
    wide fstore f_408;
    ir1481: ldc2 double_304; // 292.0
    wide dstore d_409;
    ir1488: sipush 293;
    wide istore i_411;
    ir1495: ldc2 long_306;
    wide lstore l_412;
    ir1502: aconst_null;
    wide astore a_414;
    ir1507: ldc float_308; // 296.0
    wide fstore f_415;
    ir1514: ldc2 double_309; // 297.0
    wide dstore d_416;
    ir1521: sipush 298;
    wide istore i_418;
    ir1528: ldc2 long_311;
    wide lstore l_419;
    ir1535: wide iinc i_418, 1;
    ir1541: new classref_313; // java/lang/StringBuilder
    dup;
    invokespecial methodref_315; // class=java/lang/StringBuilder, name=<init>, descriptor=()V
    aload a_1;
    invokevirtual methodref_316; // class=java/lang/StringBuilder, name=append, descriptor=(Ljava/lang/Object;)Ljava/lang/StringBuilder;
    fload f_2;
    invokevirtual methodref_320; // class=java/lang/StringBuilder, name=append, descriptor=(F)Ljava/lang/StringBuilder;
    dload d_3;
    invokevirtual methodref_323; // class=java/lang/StringBuilder, name=append, descriptor=(D)Ljava/lang/StringBuilder;
    iload i_5;
    invokevirtual methodref_326; // class=java/lang/StringBuilder, name=append, descriptor=(I)Ljava/lang/StringBuilder;
    lload l_6;
    invokevirtual methodref_329; // class=java/lang/StringBuilder, name=append, descriptor=(J)Ljava/lang/StringBuilder;
    aload a_8;
    invokevirtual methodref_316; // class=java/lang/StringBuilder, name=append, descriptor=(Ljava/lang/Object;)Ljava/lang/StringBuilder;
    fload f_9;
    invokevirtual methodref_320; // class=java/lang/StringBuilder, name=append, descriptor=(F)Ljava/lang/StringBuilder;
    dload d_10;
    invokevirtual methodref_323; // class=java/lang/StringBuilder, name=append, descriptor=(D)Ljava/lang/StringBuilder;
    iload i_12;
    invokevirtual methodref_326; // class=java/lang/StringBuilder, name=append, descriptor=(I)Ljava/lang/StringBuilder;
    lload l_13;
    invokevirtual methodref_329; // class=java/lang/StringBuilder, name=append, descriptor=(J)Ljava/lang/StringBuilder;
    aload a_15;
    invokevirtual methodref_316; // class=java/lang/StringBuilder, name=append, descriptor=(Ljava/lang/Object;)Ljava/lang/StringBuilder;
    fload f_16;
    invokevirtual methodref_320; // class=java/lang/StringBuilder, name=append, descriptor=(F)Ljava/lang/StringBuilder;
    dload d_17;
    invokevirtual methodref_323; // class=java/lang/StringBuilder, name=append, descriptor=(D)Ljava/lang/StringBuilder;
    iload i_19;
    invokevirtual methodref_326; // class=java/lang/StringBuilder, name=append, descriptor=(I)Ljava/lang/StringBuilder;
    lload l_20;
    invokevirtual methodref_329; // class=java/lang/StringBuilder, name=append, descriptor=(J)Ljava/lang/StringBuilder;
    aload a_22;
    invokevirtual methodref_316; // class=java/lang/StringBuilder, name=append, descriptor=(Ljava/lang/Object;)Ljava/lang/StringBuilder;
    fload f_23;
    invokevirtual methodref_320; // class=java/lang/StringBuilder, name=append, descriptor=(F)Ljava/lang/StringBuilder;
    dload d_24;
    invokevirtual methodref_323; // class=java/lang/StringBuilder, name=append, descriptor=(D)Ljava/lang/StringBuilder;
    iload i_26;
    invokevirtual methodref_326; // class=java/lang/StringBuilder, name=append, descriptor=(I)Ljava/lang/StringBuilder;
    lload l_27;
    invokevirtual methodref_329; // class=java/lang/StringBuilder, name=append, descriptor=(J)Ljava/lang/StringBuilder;
    aload a_29;
    invokevirtual methodref_316; // class=java/lang/StringBuilder, name=append, descriptor=(Ljava/lang/Object;)Ljava/lang/StringBuilder;
    fload f_30;
    invokevirtual methodref_320; // class=java/lang/StringBuilder, name=append, descriptor=(F)Ljava/lang/StringBuilder;
    dload d_31;
    invokevirtual methodref_323; // class=java/lang/StringBuilder, name=append, descriptor=(D)Ljava/lang/StringBuilder;
    iload i_33;
    invokevirtual methodref_326; // class=java/lang/StringBuilder, name=append, descriptor=(I)Ljava/lang/StringBuilder;
    lload l_34;
    invokevirtual methodref_329; // class=java/lang/StringBuilder, name=append, descriptor=(J)Ljava/lang/StringBuilder;
    aload a_36;
    invokevirtual methodref_316; // class=java/lang/StringBuilder, name=append, descriptor=(Ljava/lang/Object;)Ljava/lang/StringBuilder;
    fload f_37;
    invokevirtual methodref_320; // class=java/lang/StringBuilder, name=append, descriptor=(F)Ljava/lang/StringBuilder;
    dload d_38;
    invokevirtual methodref_323; // class=java/lang/StringBuilder, name=append, descriptor=(D)Ljava/lang/StringBuilder;
    iload i_40;
    invokevirtual methodref_326; // class=java/lang/StringBuilder, name=append, descriptor=(I)Ljava/lang/StringBuilder;
    lload l_41;
    invokevirtual methodref_329; // class=java/lang/StringBuilder, name=append, descriptor=(J)Ljava/lang/StringBuilder;
    aload a_43;
    invokevirtual methodref_316; // class=java/lang/StringBuilder, name=append, descriptor=(Ljava/lang/Object;)Ljava/lang/StringBuilder;
    fload f_44;
    invokevirtual methodref_320; // class=java/lang/StringBuilder, name=append, descriptor=(F)Ljava/lang/StringBuilder;
    dload d_45;
    invokevirtual methodref_323; // class=java/lang/StringBuilder, name=append, descriptor=(D)Ljava/lang/StringBuilder;
    iload i_47;
    invokevirtual methodref_326; // class=java/lang/StringBuilder, name=append, descriptor=(I)Ljava/lang/StringBuilder;
    lload l_48;
    invokevirtual methodref_329; // class=java/lang/StringBuilder, name=append, descriptor=(J)Ljava/lang/StringBuilder;
    aload a_50;
    invokevirtual methodref_316; // class=java/lang/StringBuilder, name=append, descriptor=(Ljava/lang/Object;)Ljava/lang/StringBuilder;
    fload f_51;
    invokevirtual methodref_320; // class=java/lang/StringBuilder, name=append, descriptor=(F)Ljava/lang/StringBuilder;
    dload d_52;
    invokevirtual methodref_323; // class=java/lang/StringBuilder, name=append, descriptor=(D)Ljava/lang/StringBuilder;
    iload i_54;
    invokevirtual methodref_326; // class=java/lang/StringBuilder, name=append, descriptor=(I)Ljava/lang/StringBuilder;
    lload l_55;
    invokevirtual methodref_329; // class=java/lang/StringBuilder, name=append, descriptor=(J)Ljava/lang/StringBuilder;
    aload a_57;
    invokevirtual methodref_316; // class=java/lang/StringBuilder, name=append, descriptor=(Ljava/lang/Object;)Ljava/lang/StringBuilder;
    fload f_58;
    invokevirtual methodref_320; // class=java/lang/StringBuilder, name=append, descriptor=(F)Ljava/lang/StringBuilder;
    dload d_59;
    invokevirtual methodref_323; // class=java/lang/StringBuilder, name=append, descriptor=(D)Ljava/lang/StringBuilder;
    iload i_61;
    invokevirtual methodref_326; // class=java/lang/StringBuilder, name=append, descriptor=(I)Ljava/lang/StringBuilder;
    lload l_62;
    invokevirtual methodref_329; // class=java/lang/StringBuilder, name=append, descriptor=(J)Ljava/lang/StringBuilder;
    aload a_64;
    invokevirtual methodref_316; // class=java/lang/StringBuilder, name=append, descriptor=(Ljava/lang/Object;)Ljava/lang/StringBuilder;
    fload f_65;
    invokevirtual methodref_320; // class=java/lang/StringBuilder, name=append, descriptor=(F)Ljava/lang/StringBuilder;
    dload d_66;
    invokevirtual methodref_323; // class=java/lang/StringBuilder, name=append, descriptor=(D)Ljava/lang/StringBuilder;
    iload i_68;
    invokevirtual methodref_326; // class=java/lang/StringBuilder, name=append, descriptor=(I)Ljava/lang/StringBuilder;
    lload l_69;
    invokevirtual methodref_329; // class=java/lang/StringBuilder, name=append, descriptor=(J)Ljava/lang/StringBuilder;
    aload a_71;
    invokevirtual methodref_316; // class=java/lang/StringBuilder, name=append, descriptor=(Ljava/lang/Object;)Ljava/lang/StringBuilder;
    fload f_72;
    invokevirtual methodref_320; // class=java/lang/StringBuilder, name=append, descriptor=(F)Ljava/lang/StringBuilder;
    dload d_73;
    invokevirtual methodref_323; // class=java/lang/StringBuilder, name=append, descriptor=(D)Ljava/lang/StringBuilder;
    iload i_75;
    invokevirtual methodref_326; // class=java/lang/StringBuilder, name=append, descriptor=(I)Ljava/lang/StringBuilder;
    lload l_76;
    invokevirtual methodref_329; // class=java/lang/StringBuilder, name=append, descriptor=(J)Ljava/lang/StringBuilder;
    aload a_78;
    invokevirtual methodref_316; // class=java/lang/StringBuilder, name=append, descriptor=(Ljava/lang/Object;)Ljava/lang/StringBuilder;
    fload f_79;
    invokevirtual methodref_320; // class=java/lang/StringBuilder, name=append, descriptor=(F)Ljava/lang/StringBuilder;
    dload d_80;
    invokevirtual methodref_323; // class=java/lang/StringBuilder, name=append, descriptor=(D)Ljava/lang/StringBuilder;
    iload i_82;
    invokevirtual methodref_326; // class=java/lang/StringBuilder, name=append, descriptor=(I)Ljava/lang/StringBuilder;
    lload l_83;
    invokevirtual methodref_329; // class=java/lang/StringBuilder, name=append, descriptor=(J)Ljava/lang/StringBuilder;
    aload a_85;
    invokevirtual methodref_316; // class=java/lang/StringBuilder, name=append, descriptor=(Ljava/lang/Object;)Ljava/lang/StringBuilder;
    fload f_86;
    invokevirtual methodref_320; // class=java/lang/StringBuilder, name=append, descriptor=(F)Ljava/lang/StringBuilder;
    dload d_87;
    invokevirtual methodref_323; // class=java/lang/StringBuilder, name=append, descriptor=(D)Ljava/lang/StringBuilder;
    iload i_89;
    invokevirtual methodref_326; // class=java/lang/StringBuilder, name=append, descriptor=(I)Ljava/lang/StringBuilder;
    lload l_90;
    invokevirtual methodref_329; // class=java/lang/StringBuilder, name=append, descriptor=(J)Ljava/lang/StringBuilder;
    aload a_92;
    invokevirtual methodref_316; // class=java/lang/StringBuilder, name=append, descriptor=(Ljava/lang/Object;)Ljava/lang/StringBuilder;
    fload f_93;
    invokevirtual methodref_320; // class=java/lang/StringBuilder, name=append, descriptor=(F)Ljava/lang/StringBuilder;
    dload d_94;
    invokevirtual methodref_323; // class=java/lang/StringBuilder, name=append, descriptor=(D)Ljava/lang/StringBuilder;
    iload i_96;
    invokevirtual methodref_326; // class=java/lang/StringBuilder, name=append, descriptor=(I)Ljava/lang/StringBuilder;
    lload l_97;
    invokevirtual methodref_329; // class=java/lang/StringBuilder, name=append, descriptor=(J)Ljava/lang/StringBuilder;
    aload a_99;
    invokevirtual methodref_316; // class=java/lang/StringBuilder, name=append, descriptor=(Ljava/lang/Object;)Ljava/lang/StringBuilder;
    fload f_100;
    invokevirtual methodref_320; // class=java/lang/StringBuilder, name=append, descriptor=(F)Ljava/lang/StringBuilder;
    dload d_101;
    invokevirtual methodref_323; // class=java/lang/StringBuilder, name=append, descriptor=(D)Ljava/lang/StringBuilder;
    iload i_103;
    invokevirtual methodref_326; // class=java/lang/StringBuilder, name=append, descriptor=(I)Ljava/lang/StringBuilder;
    lload l_104;
    invokevirtual methodref_329; // class=java/lang/StringBuilder, name=append, descriptor=(J)Ljava/lang/StringBuilder;
    aload a_106;
    invokevirtual methodref_316; // class=java/lang/StringBuilder, name=append, descriptor=(Ljava/lang/Object;)Ljava/lang/StringBuilder;
    fload f_107;
    invokevirtual methodref_320; // class=java/lang/StringBuilder, name=append, descriptor=(F)Ljava/lang/StringBuilder;
    dload d_108;
    invokevirtual methodref_323; // class=java/lang/StringBuilder, name=append, descriptor=(D)Ljava/lang/StringBuilder;
    iload i_110;
    invokevirtual methodref_326; // class=java/lang/StringBuilder, name=append, descriptor=(I)Ljava/lang/StringBuilder;
    lload l_111;
    invokevirtual methodref_329; // class=java/lang/StringBuilder, name=append, descriptor=(J)Ljava/lang/StringBuilder;
    aload a_113;
    invokevirtual methodref_316; // class=java/lang/StringBuilder, name=append, descriptor=(Ljava/lang/Object;)Ljava/lang/StringBuilder;
    fload f_114;
    invokevirtual methodref_320; // class=java/lang/StringBuilder, name=append, descriptor=(F)Ljava/lang/StringBuilder;
    dload d_115;
    invokevirtual methodref_323; // class=java/lang/StringBuilder, name=append, descriptor=(D)Ljava/lang/StringBuilder;
    iload i_117;
    invokevirtual methodref_326; // class=java/lang/StringBuilder, name=append, descriptor=(I)Ljava/lang/StringBuilder;
    lload l_118;
    invokevirtual methodref_329; // class=java/lang/StringBuilder, name=append, descriptor=(J)Ljava/lang/StringBuilder;
    aload a_120;
    invokevirtual methodref_316; // class=java/lang/StringBuilder, name=append, descriptor=(Ljava/lang/Object;)Ljava/lang/StringBuilder;
    fload f_121;
    invokevirtual methodref_320; // class=java/lang/StringBuilder, name=append, descriptor=(F)Ljava/lang/StringBuilder;
    dload d_122;
    invokevirtual methodref_323; // class=java/lang/StringBuilder, name=append, descriptor=(D)Ljava/lang/StringBuilder;
    iload i_124;
    invokevirtual methodref_326; // class=java/lang/StringBuilder, name=append, descriptor=(I)Ljava/lang/StringBuilder;
    lload l_125;
    invokevirtual methodref_329; // class=java/lang/StringBuilder, name=append, descriptor=(J)Ljava/lang/StringBuilder;
    aload a_127;
    invokevirtual methodref_316; // class=java/lang/StringBuilder, name=append, descriptor=(Ljava/lang/Object;)Ljava/lang/StringBuilder;
    fload f_128;
    invokevirtual methodref_320; // class=java/lang/StringBuilder, name=append, descriptor=(F)Ljava/lang/StringBuilder;
    dload d_129;
    invokevirtual methodref_323; // class=java/lang/StringBuilder, name=append, descriptor=(D)Ljava/lang/StringBuilder;
    iload i_131;
    invokevirtual methodref_326; // class=java/lang/StringBuilder, name=append, descriptor=(I)Ljava/lang/StringBuilder;
    lload l_132;
    invokevirtual methodref_329; // class=java/lang/StringBuilder, name=append, descriptor=(J)Ljava/lang/StringBuilder;
    aload a_134;
    invokevirtual methodref_316; // class=java/lang/StringBuilder, name=append, descriptor=(Ljava/lang/Object;)Ljava/lang/StringBuilder;
    fload f_135;
    invokevirtual methodref_320; // class=java/lang/StringBuilder, name=append, descriptor=(F)Ljava/lang/StringBuilder;
    dload d_136;
    invokevirtual methodref_323; // class=java/lang/StringBuilder, name=append, descriptor=(D)Ljava/lang/StringBuilder;
    iload i_138;
    invokevirtual methodref_326; // class=java/lang/StringBuilder, name=append, descriptor=(I)Ljava/lang/StringBuilder;
    lload l_139;
    invokevirtual methodref_329; // class=java/lang/StringBuilder, name=append, descriptor=(J)Ljava/lang/StringBuilder;
    aload a_141;
    invokevirtual methodref_316; // class=java/lang/StringBuilder, name=append, descriptor=(Ljava/lang/Object;)Ljava/lang/StringBuilder;
    fload f_142;
    invokevirtual methodref_320; // class=java/lang/StringBuilder, name=append, descriptor=(F)Ljava/lang/StringBuilder;
    dload d_143;
    invokevirtual methodref_323; // class=java/lang/StringBuilder, name=append, descriptor=(D)Ljava/lang/StringBuilder;
    iload i_145;
    invokevirtual methodref_326; // class=java/lang/StringBuilder, name=append, descriptor=(I)Ljava/lang/StringBuilder;
    lload l_146;
    invokevirtual methodref_329; // class=java/lang/StringBuilder, name=append, descriptor=(J)Ljava/lang/StringBuilder;
    aload a_148;
    invokevirtual methodref_316; // class=java/lang/StringBuilder, name=append, descriptor=(Ljava/lang/Object;)Ljava/lang/StringBuilder;
    fload f_149;
    invokevirtual methodref_320; // class=java/lang/StringBuilder, name=append, descriptor=(F)Ljava/lang/StringBuilder;
    dload d_150;
    invokevirtual methodref_323; // class=java/lang/StringBuilder, name=append, descriptor=(D)Ljava/lang/StringBuilder;
    iload i_152;
    invokevirtual methodref_326; // class=java/lang/StringBuilder, name=append, descriptor=(I)Ljava/lang/StringBuilder;
    lload l_153;
    invokevirtual methodref_329; // class=java/lang/StringBuilder, name=append, descriptor=(J)Ljava/lang/StringBuilder;
    aload a_155;
    invokevirtual methodref_316; // class=java/lang/StringBuilder, name=append, descriptor=(Ljava/lang/Object;)Ljava/lang/StringBuilder;
    fload f_156;
    invokevirtual methodref_320; // class=java/lang/StringBuilder, name=append, descriptor=(F)Ljava/lang/StringBuilder;
    dload d_157;
    invokevirtual methodref_323; // class=java/lang/StringBuilder, name=append, descriptor=(D)Ljava/lang/StringBuilder;
    iload i_159;
    invokevirtual methodref_326; // class=java/lang/StringBuilder, name=append, descriptor=(I)Ljava/lang/StringBuilder;
    lload l_160;
    invokevirtual methodref_329; // class=java/lang/StringBuilder, name=append, descriptor=(J)Ljava/lang/StringBuilder;
    aload a_162;
    invokevirtual methodref_316; // class=java/lang/StringBuilder, name=append, descriptor=(Ljava/lang/Object;)Ljava/lang/StringBuilder;
    fload f_163;
    invokevirtual methodref_320; // class=java/lang/StringBuilder, name=append, descriptor=(F)Ljava/lang/StringBuilder;
    dload d_164;
    invokevirtual methodref_323; // class=java/lang/StringBuilder, name=append, descriptor=(D)Ljava/lang/StringBuilder;
    iload i_166;
    invokevirtual methodref_326; // class=java/lang/StringBuilder, name=append, descriptor=(I)Ljava/lang/StringBuilder;
    lload l_167;
    invokevirtual methodref_329; // class=java/lang/StringBuilder, name=append, descriptor=(J)Ljava/lang/StringBuilder;
    aload a_169;
    invokevirtual methodref_316; // class=java/lang/StringBuilder, name=append, descriptor=(Ljava/lang/Object;)Ljava/lang/StringBuilder;
    fload f_170;
    invokevirtual methodref_320; // class=java/lang/StringBuilder, name=append, descriptor=(F)Ljava/lang/StringBuilder;
    dload d_171;
    invokevirtual methodref_323; // class=java/lang/StringBuilder, name=append, descriptor=(D)Ljava/lang/StringBuilder;
    iload i_173;
    invokevirtual methodref_326; // class=java/lang/StringBuilder, name=append, descriptor=(I)Ljava/lang/StringBuilder;
    lload l_174;
    invokevirtual methodref_329; // class=java/lang/StringBuilder, name=append, descriptor=(J)Ljava/lang/StringBuilder;
    aload a_176;
    invokevirtual methodref_316; // class=java/lang/StringBuilder, name=append, descriptor=(Ljava/lang/Object;)Ljava/lang/StringBuilder;
    fload f_177;
    invokevirtual methodref_320; // class=java/lang/StringBuilder, name=append, descriptor=(F)Ljava/lang/StringBuilder;
    dload d_178;
    invokevirtual methodref_323; // class=java/lang/StringBuilder, name=append, descriptor=(D)Ljava/lang/StringBuilder;
    iload i_180;
    invokevirtual methodref_326; // class=java/lang/StringBuilder, name=append, descriptor=(I)Ljava/lang/StringBuilder;
    lload l_181;
    invokevirtual methodref_329; // class=java/lang/StringBuilder, name=append, descriptor=(J)Ljava/lang/StringBuilder;
    aload a_183;
    invokevirtual methodref_316; // class=java/lang/StringBuilder, name=append, descriptor=(Ljava/lang/Object;)Ljava/lang/StringBuilder;
    fload f_184;
    invokevirtual methodref_320; // class=java/lang/StringBuilder, name=append, descriptor=(F)Ljava/lang/StringBuilder;
    dload d_185;
    invokevirtual methodref_323; // class=java/lang/StringBuilder, name=append, descriptor=(D)Ljava/lang/StringBuilder;
    iload i_187;
    invokevirtual methodref_326; // class=java/lang/StringBuilder, name=append, descriptor=(I)Ljava/lang/StringBuilder;
    lload l_188;
    invokevirtual methodref_329; // class=java/lang/StringBuilder, name=append, descriptor=(J)Ljava/lang/StringBuilder;
    aload a_190;
    invokevirtual methodref_316; // class=java/lang/StringBuilder, name=append, descriptor=(Ljava/lang/Object;)Ljava/lang/StringBuilder;
    fload f_191;
    invokevirtual methodref_320; // class=java/lang/StringBuilder, name=append, descriptor=(F)Ljava/lang/StringBuilder;
    dload d_192;
    invokevirtual methodref_323; // class=java/lang/StringBuilder, name=append, descriptor=(D)Ljava/lang/StringBuilder;
    iload i_194;
    invokevirtual methodref_326; // class=java/lang/StringBuilder, name=append, descriptor=(I)Ljava/lang/StringBuilder;
    lload l_195;
    invokevirtual methodref_329; // class=java/lang/StringBuilder, name=append, descriptor=(J)Ljava/lang/StringBuilder;
    aload a_197;
    invokevirtual methodref_316; // class=java/lang/StringBuilder, name=append, descriptor=(Ljava/lang/Object;)Ljava/lang/StringBuilder;
    fload f_198;
    invokevirtual methodref_320; // class=java/lang/StringBuilder, name=append, descriptor=(F)Ljava/lang/StringBuilder;
    dload d_199;
    invokevirtual methodref_323; // class=java/lang/StringBuilder, name=append, descriptor=(D)Ljava/lang/StringBuilder;
    iload i_201;
    invokevirtual methodref_326; // class=java/lang/StringBuilder, name=append, descriptor=(I)Ljava/lang/StringBuilder;
    lload l_202;
    invokevirtual methodref_329; // class=java/lang/StringBuilder, name=append, descriptor=(J)Ljava/lang/StringBuilder;
    aload a_204;
    invokevirtual methodref_316; // class=java/lang/StringBuilder, name=append, descriptor=(Ljava/lang/Object;)Ljava/lang/StringBuilder;
    fload f_205;
    invokevirtual methodref_320; // class=java/lang/StringBuilder, name=append, descriptor=(F)Ljava/lang/StringBuilder;
    dload d_206;
    invokevirtual methodref_323; // class=java/lang/StringBuilder, name=append, descriptor=(D)Ljava/lang/StringBuilder;
    iload i_208;
    invokevirtual methodref_326; // class=java/lang/StringBuilder, name=append, descriptor=(I)Ljava/lang/StringBuilder;
    lload l_209;
    invokevirtual methodref_329; // class=java/lang/StringBuilder, name=append, descriptor=(J)Ljava/lang/StringBuilder;
    aload a_211;
    invokevirtual methodref_316; // class=java/lang/StringBuilder, name=append, descriptor=(Ljava/lang/Object;)Ljava/lang/StringBuilder;
    fload f_212;
    invokevirtual methodref_320; // class=java/lang/StringBuilder, name=append, descriptor=(F)Ljava/lang/StringBuilder;
    dload d_213;
    invokevirtual methodref_323; // class=java/lang/StringBuilder, name=append, descriptor=(D)Ljava/lang/StringBuilder;
    iload i_215;
    invokevirtual methodref_326; // class=java/lang/StringBuilder, name=append, descriptor=(I)Ljava/lang/StringBuilder;
    lload l_216;
    invokevirtual methodref_329; // class=java/lang/StringBuilder, name=append, descriptor=(J)Ljava/lang/StringBuilder;
    aload a_218;
    invokevirtual methodref_316; // class=java/lang/StringBuilder, name=append, descriptor=(Ljava/lang/Object;)Ljava/lang/StringBuilder;
    fload f_219;
    invokevirtual methodref_320; // class=java/lang/StringBuilder, name=append, descriptor=(F)Ljava/lang/StringBuilder;
    dload d_220;
    invokevirtual methodref_323; // class=java/lang/StringBuilder, name=append, descriptor=(D)Ljava/lang/StringBuilder;
    iload i_222;
    invokevirtual methodref_326; // class=java/lang/StringBuilder, name=append, descriptor=(I)Ljava/lang/StringBuilder;
    lload l_223;
    invokevirtual methodref_329; // class=java/lang/StringBuilder, name=append, descriptor=(J)Ljava/lang/StringBuilder;
    aload a_225;
    invokevirtual methodref_316; // class=java/lang/StringBuilder, name=append, descriptor=(Ljava/lang/Object;)Ljava/lang/StringBuilder;
    fload f_226;
    invokevirtual methodref_320; // class=java/lang/StringBuilder, name=append, descriptor=(F)Ljava/lang/StringBuilder;
    dload d_227;
    invokevirtual methodref_323; // class=java/lang/StringBuilder, name=append, descriptor=(D)Ljava/lang/StringBuilder;
    iload i_229;
    invokevirtual methodref_326; // class=java/lang/StringBuilder, name=append, descriptor=(I)Ljava/lang/StringBuilder;
    lload l_230;
    invokevirtual methodref_329; // class=java/lang/StringBuilder, name=append, descriptor=(J)Ljava/lang/StringBuilder;
    aload a_232;
    invokevirtual methodref_316; // class=java/lang/StringBuilder, name=append, descriptor=(Ljava/lang/Object;)Ljava/lang/StringBuilder;
    fload f_233;
    invokevirtual methodref_320; // class=java/lang/StringBuilder, name=append, descriptor=(F)Ljava/lang/StringBuilder;
    dload d_234;
    invokevirtual methodref_323; // class=java/lang/StringBuilder, name=append, descriptor=(D)Ljava/lang/StringBuilder;
    iload i_236;
    invokevirtual methodref_326; // class=java/lang/StringBuilder, name=append, descriptor=(I)Ljava/lang/StringBuilder;
    lload l_237;
    invokevirtual methodref_329; // class=java/lang/StringBuilder, name=append, descriptor=(J)Ljava/lang/StringBuilder;
    aload a_239;
    invokevirtual methodref_316; // class=java/lang/StringBuilder, name=append, descriptor=(Ljava/lang/Object;)Ljava/lang/StringBuilder;
    fload f_240;
    invokevirtual methodref_320; // class=java/lang/StringBuilder, name=append, descriptor=(F)Ljava/lang/StringBuilder;
    dload d_241;
    invokevirtual methodref_323; // class=java/lang/StringBuilder, name=append, descriptor=(D)Ljava/lang/StringBuilder;
    iload i_243;
    invokevirtual methodref_326; // class=java/lang/StringBuilder, name=append, descriptor=(I)Ljava/lang/StringBuilder;
    lload l_244;
    invokevirtual methodref_329; // class=java/lang/StringBuilder, name=append, descriptor=(J)Ljava/lang/StringBuilder;
    aload a_246;
    invokevirtual methodref_316; // class=java/lang/StringBuilder, name=append, descriptor=(Ljava/lang/Object;)Ljava/lang/StringBuilder;
    fload f_247;
    invokevirtual methodref_320; // class=java/lang/StringBuilder, name=append, descriptor=(F)Ljava/lang/StringBuilder;
    dload d_248;
    invokevirtual methodref_323; // class=java/lang/StringBuilder, name=append, descriptor=(D)Ljava/lang/StringBuilder;
    iload i_250;
    invokevirtual methodref_326; // class=java/lang/StringBuilder, name=append, descriptor=(I)Ljava/lang/StringBuilder;
    lload l_251;
    invokevirtual methodref_329; // class=java/lang/StringBuilder, name=append, descriptor=(J)Ljava/lang/StringBuilder;
    aload a_253;
    invokevirtual methodref_316; // class=java/lang/StringBuilder, name=append, descriptor=(Ljava/lang/Object;)Ljava/lang/StringBuilder;
    fload f_254;
    invokevirtual methodref_320; // class=java/lang/StringBuilder, name=append, descriptor=(F)Ljava/lang/StringBuilder;
    dload d_255;
    invokevirtual methodref_323; // class=java/lang/StringBuilder, name=append, descriptor=(D)Ljava/lang/StringBuilder;
    wide iload i_257;
    invokevirtual methodref_326; // class=java/lang/StringBuilder, name=append, descriptor=(I)Ljava/lang/StringBuilder;
    wide lload l_258;
    invokevirtual methodref_329; // class=java/lang/StringBuilder, name=append, descriptor=(J)Ljava/lang/StringBuilder;
    wide aload a_260;
    invokevirtual methodref_316; // class=java/lang/StringBuilder, name=append, descriptor=(Ljava/lang/Object;)Ljava/lang/StringBuilder;
    wide fload f_261;
    invokevirtual methodref_320; // class=java/lang/StringBuilder, name=append, descriptor=(F)Ljava/lang/StringBuilder;
    wide dload d_262;
    invokevirtual methodref_323; // class=java/lang/StringBuilder, name=append, descriptor=(D)Ljava/lang/StringBuilder;
    wide iload i_264;
    invokevirtual methodref_326; // class=java/lang/StringBuilder, name=append, descriptor=(I)Ljava/lang/StringBuilder;
    wide lload l_265;
    invokevirtual methodref_329; // class=java/lang/StringBuilder, name=append, descriptor=(J)Ljava/lang/StringBuilder;
    wide aload a_267;
    invokevirtual methodref_316; // class=java/lang/StringBuilder, name=append, descriptor=(Ljava/lang/Object;)Ljava/lang/StringBuilder;
    wide fload f_268;
    invokevirtual methodref_320; // class=java/lang/StringBuilder, name=append, descriptor=(F)Ljava/lang/StringBuilder;
    wide dload d_269;
    invokevirtual methodref_323; // class=java/lang/StringBuilder, name=append, descriptor=(D)Ljava/lang/StringBuilder;
    wide iload i_271;
    invokevirtual methodref_326; // class=java/lang/StringBuilder, name=append, descriptor=(I)Ljava/lang/StringBuilder;
    wide lload l_272;
    invokevirtual methodref_329; // class=java/lang/StringBuilder, name=append, descriptor=(J)Ljava/lang/StringBuilder;
    wide aload a_274;
    invokevirtual methodref_316; // class=java/lang/StringBuilder, name=append, descriptor=(Ljava/lang/Object;)Ljava/lang/StringBuilder;
    wide fload f_275;
    invokevirtual methodref_320; // class=java/lang/StringBuilder, name=append, descriptor=(F)Ljava/lang/StringBuilder;
    wide dload d_276;
    invokevirtual methodref_323; // class=java/lang/StringBuilder, name=append, descriptor=(D)Ljava/lang/StringBuilder;
    wide iload i_278;
    invokevirtual methodref_326; // class=java/lang/StringBuilder, name=append, descriptor=(I)Ljava/lang/StringBuilder;
    wide lload l_279;
    invokevirtual methodref_329; // class=java/lang/StringBuilder, name=append, descriptor=(J)Ljava/lang/StringBuilder;
    wide aload a_281;
    invokevirtual methodref_316; // class=java/lang/StringBuilder, name=append, descriptor=(Ljava/lang/Object;)Ljava/lang/StringBuilder;
    wide fload f_282;
    invokevirtual methodref_320; // class=java/lang/StringBuilder, name=append, descriptor=(F)Ljava/lang/StringBuilder;
    wide dload d_283;
    invokevirtual methodref_323; // class=java/lang/StringBuilder, name=append, descriptor=(D)Ljava/lang/StringBuilder;
    wide iload i_285;
    invokevirtual methodref_326; // class=java/lang/StringBuilder, name=append, descriptor=(I)Ljava/lang/StringBuilder;
    wide lload l_286;
    invokevirtual methodref_329; // class=java/lang/StringBuilder, name=append, descriptor=(J)Ljava/lang/StringBuilder;
    wide aload a_288;
    invokevirtual methodref_316; // class=java/lang/StringBuilder, name=append, descriptor=(Ljava/lang/Object;)Ljava/lang/StringBuilder;
    wide fload f_289;
    invokevirtual methodref_320; // class=java/lang/StringBuilder, name=append, descriptor=(F)Ljava/lang/StringBuilder;
    wide dload d_290;
    invokevirtual methodref_323; // class=java/lang/StringBuilder, name=append, descriptor=(D)Ljava/lang/StringBuilder;
    wide iload i_292;
    invokevirtual methodref_326; // class=java/lang/StringBuilder, name=append, descriptor=(I)Ljava/lang/StringBuilder;
    wide lload l_293;
    invokevirtual methodref_329; // class=java/lang/StringBuilder, name=append, descriptor=(J)Ljava/lang/StringBuilder;
    wide aload a_295;
    invokevirtual methodref_316; // class=java/lang/StringBuilder, name=append, descriptor=(Ljava/lang/Object;)Ljava/lang/StringBuilder;
    wide fload f_296;
    invokevirtual methodref_320; // class=java/lang/StringBuilder, name=append, descriptor=(F)Ljava/lang/StringBuilder;
    wide dload d_297;
    invokevirtual methodref_323; // class=java/lang/StringBuilder, name=append, descriptor=(D)Ljava/lang/StringBuilder;
    wide iload i_299;
    invokevirtual methodref_326; // class=java/lang/StringBuilder, name=append, descriptor=(I)Ljava/lang/StringBuilder;
    wide lload l_300;
    invokevirtual methodref_329; // class=java/lang/StringBuilder, name=append, descriptor=(J)Ljava/lang/StringBuilder;
    wide aload a_302;
    invokevirtual methodref_316; // class=java/lang/StringBuilder, name=append, descriptor=(Ljava/lang/Object;)Ljava/lang/StringBuilder;
    wide fload f_303;
    invokevirtual methodref_320; // class=java/lang/StringBuilder, name=append, descriptor=(F)Ljava/lang/StringBuilder;
    wide dload d_304;
    invokevirtual methodref_323; // class=java/lang/StringBuilder, name=append, descriptor=(D)Ljava/lang/StringBuilder;
    wide iload i_306;
    invokevirtual methodref_326; // class=java/lang/StringBuilder, name=append, descriptor=(I)Ljava/lang/StringBuilder;
    wide lload l_307;
    invokevirtual methodref_329; // class=java/lang/StringBuilder, name=append, descriptor=(J)Ljava/lang/StringBuilder;
    wide aload a_309;
    invokevirtual methodref_316; // class=java/lang/StringBuilder, name=append, descriptor=(Ljava/lang/Object;)Ljava/lang/StringBuilder;
    wide fload f_310;
    invokevirtual methodref_320; // class=java/lang/StringBuilder, name=append, descriptor=(F)Ljava/lang/StringBuilder;
    wide dload d_311;
    invokevirtual methodref_323; // class=java/lang/StringBuilder, name=append, descriptor=(D)Ljava/lang/StringBuilder;
    wide iload i_313;
    invokevirtual methodref_326; // class=java/lang/StringBuilder, name=append, descriptor=(I)Ljava/lang/StringBuilder;
    wide lload l_314;
    invokevirtual methodref_329; // class=java/lang/StringBuilder, name=append, descriptor=(J)Ljava/lang/StringBuilder;
    wide aload a_316;
    invokevirtual methodref_316; // class=java/lang/StringBuilder, name=append, descriptor=(Ljava/lang/Object;)Ljava/lang/StringBuilder;
    wide fload f_317;
    invokevirtual methodref_320; // class=java/lang/StringBuilder, name=append, descriptor=(F)Ljava/lang/StringBuilder;
    wide dload d_318;
    invokevirtual methodref_323; // class=java/lang/StringBuilder, name=append, descriptor=(D)Ljava/lang/StringBuilder;
    wide iload i_320;
    invokevirtual methodref_326; // class=java/lang/StringBuilder, name=append, descriptor=(I)Ljava/lang/StringBuilder;
    wide lload l_321;
    invokevirtual methodref_329; // class=java/lang/StringBuilder, name=append, descriptor=(J)Ljava/lang/StringBuilder;
    wide aload a_323;
    invokevirtual methodref_316; // class=java/lang/StringBuilder, name=append, descriptor=(Ljava/lang/Object;)Ljava/lang/StringBuilder;
    wide fload f_324;
    invokevirtual methodref_320; // class=java/lang/StringBuilder, name=append, descriptor=(F)Ljava/lang/StringBuilder;
    wide dload d_325;
    invokevirtual methodref_323; // class=java/lang/StringBuilder, name=append, descriptor=(D)Ljava/lang/StringBuilder;
    wide iload i_327;
    invokevirtual methodref_326; // class=java/lang/StringBuilder, name=append, descriptor=(I)Ljava/lang/StringBuilder;
    wide lload l_328;
    invokevirtual methodref_329; // class=java/lang/StringBuilder, name=append, descriptor=(J)Ljava/lang/StringBuilder;
    wide aload a_330;
    invokevirtual methodref_316; // class=java/lang/StringBuilder, name=append, descriptor=(Ljava/lang/Object;)Ljava/lang/StringBuilder;
    wide fload f_331;
    invokevirtual methodref_320; // class=java/lang/StringBuilder, name=append, descriptor=(F)Ljava/lang/StringBuilder;
    wide dload d_332;
    invokevirtual methodref_323; // class=java/lang/StringBuilder, name=append, descriptor=(D)Ljava/lang/StringBuilder;
    wide iload i_334;
    invokevirtual methodref_326; // class=java/lang/StringBuilder, name=append, descriptor=(I)Ljava/lang/StringBuilder;
    wide lload l_335;
    invokevirtual methodref_329; // class=java/lang/StringBuilder, name=append, descriptor=(J)Ljava/lang/StringBuilder;
    wide aload a_337;
    invokevirtual methodref_316; // class=java/lang/StringBuilder, name=append, descriptor=(Ljava/lang/Object;)Ljava/lang/StringBuilder;
    wide fload f_338;
    invokevirtual methodref_320; // class=java/lang/StringBuilder, name=append, descriptor=(F)Ljava/lang/StringBuilder;
    wide dload d_339;
    invokevirtual methodref_323; // class=java/lang/StringBuilder, name=append, descriptor=(D)Ljava/lang/StringBuilder;
    wide iload i_341;
    invokevirtual methodref_326; // class=java/lang/StringBuilder, name=append, descriptor=(I)Ljava/lang/StringBuilder;
    wide lload l_342;
    invokevirtual methodref_329; // class=java/lang/StringBuilder, name=append, descriptor=(J)Ljava/lang/StringBuilder;
    wide aload a_344;
    invokevirtual methodref_316; // class=java/lang/StringBuilder, name=append, descriptor=(Ljava/lang/Object;)Ljava/lang/StringBuilder;
    wide fload f_345;
    invokevirtual methodref_320; // class=java/lang/StringBuilder, name=append, descriptor=(F)Ljava/lang/StringBuilder;
    wide dload d_346;
    invokevirtual methodref_323; // class=java/lang/StringBuilder, name=append, descriptor=(D)Ljava/lang/StringBuilder;
    wide iload i_348;
    invokevirtual methodref_326; // class=java/lang/StringBuilder, name=append, descriptor=(I)Ljava/lang/StringBuilder;
    wide lload l_349;
    invokevirtual methodref_329; // class=java/lang/StringBuilder, name=append, descriptor=(J)Ljava/lang/StringBuilder;
    wide aload a_351;
    invokevirtual methodref_316; // class=java/lang/StringBuilder, name=append, descriptor=(Ljava/lang/Object;)Ljava/lang/StringBuilder;
    wide fload f_352;
    invokevirtual methodref_320; // class=java/lang/StringBuilder, name=append, descriptor=(F)Ljava/lang/StringBuilder;
    wide dload d_353;
    invokevirtual methodref_323; // class=java/lang/StringBuilder, name=append, descriptor=(D)Ljava/lang/StringBuilder;
    wide iload i_355;
    invokevirtual methodref_326; // class=java/lang/StringBuilder, name=append, descriptor=(I)Ljava/lang/StringBuilder;
    wide lload l_356;
    invokevirtual methodref_329; // class=java/lang/StringBuilder, name=append, descriptor=(J)Ljava/lang/StringBuilder;
    wide aload a_358;
    invokevirtual methodref_316; // class=java/lang/StringBuilder, name=append, descriptor=(Ljava/lang/Object;)Ljava/lang/StringBuilder;
    wide fload f_359;
    invokevirtual methodref_320; // class=java/lang/StringBuilder, name=append, descriptor=(F)Ljava/lang/StringBuilder;
    wide dload d_360;
    invokevirtual methodref_323; // class=java/lang/StringBuilder, name=append, descriptor=(D)Ljava/lang/StringBuilder;
    wide iload i_362;
    invokevirtual methodref_326; // class=java/lang/StringBuilder, name=append, descriptor=(I)Ljava/lang/StringBuilder;
    wide lload l_363;
    invokevirtual methodref_329; // class=java/lang/StringBuilder, name=append, descriptor=(J)Ljava/lang/StringBuilder;
    wide aload a_365;
    invokevirtual methodref_316; // class=java/lang/StringBuilder, name=append, descriptor=(Ljava/lang/Object;)Ljava/lang/StringBuilder;
    wide fload f_366;
    invokevirtual methodref_320; // class=java/lang/StringBuilder, name=append, descriptor=(F)Ljava/lang/StringBuilder;
    wide dload d_367;
    invokevirtual methodref_323; // class=java/lang/StringBuilder, name=append, descriptor=(D)Ljava/lang/StringBuilder;
    wide iload i_369;
    invokevirtual methodref_326; // class=java/lang/StringBuilder, name=append, descriptor=(I)Ljava/lang/StringBuilder;
    wide lload l_370;
    invokevirtual methodref_329; // class=java/lang/StringBuilder, name=append, descriptor=(J)Ljava/lang/StringBuilder;
    wide aload a_372;
    invokevirtual methodref_316; // class=java/lang/StringBuilder, name=append, descriptor=(Ljava/lang/Object;)Ljava/lang/StringBuilder;
    wide fload f_373;
    invokevirtual methodref_320; // class=java/lang/StringBuilder, name=append, descriptor=(F)Ljava/lang/StringBuilder;
    wide dload d_374;
    invokevirtual methodref_323; // class=java/lang/StringBuilder, name=append, descriptor=(D)Ljava/lang/StringBuilder;
    wide iload i_376;
    invokevirtual methodref_326; // class=java/lang/StringBuilder, name=append, descriptor=(I)Ljava/lang/StringBuilder;
    wide lload l_377;
    invokevirtual methodref_329; // class=java/lang/StringBuilder, name=append, descriptor=(J)Ljava/lang/StringBuilder;
    wide aload a_379;
    invokevirtual methodref_316; // class=java/lang/StringBuilder, name=append, descriptor=(Ljava/lang/Object;)Ljava/lang/StringBuilder;
    wide fload f_380;
    invokevirtual methodref_320; // class=java/lang/StringBuilder, name=append, descriptor=(F)Ljava/lang/StringBuilder;
    wide dload d_381;
    invokevirtual methodref_323; // class=java/lang/StringBuilder, name=append, descriptor=(D)Ljava/lang/StringBuilder;
    wide iload i_383;
    invokevirtual methodref_326; // class=java/lang/StringBuilder, name=append, descriptor=(I)Ljava/lang/StringBuilder;
    wide lload l_384;
    invokevirtual methodref_329; // class=java/lang/StringBuilder, name=append, descriptor=(J)Ljava/lang/StringBuilder;
    wide aload a_386;
    invokevirtual methodref_316; // class=java/lang/StringBuilder, name=append, descriptor=(Ljava/lang/Object;)Ljava/lang/StringBuilder;
    wide fload f_387;
    invokevirtual methodref_320; // class=java/lang/StringBuilder, name=append, descriptor=(F)Ljava/lang/StringBuilder;
    wide dload d_388;
    invokevirtual methodref_323; // class=java/lang/StringBuilder, name=append, descriptor=(D)Ljava/lang/StringBuilder;
    wide iload i_390;
    invokevirtual methodref_326; // class=java/lang/StringBuilder, name=append, descriptor=(I)Ljava/lang/StringBuilder;
    wide lload l_391;
    invokevirtual methodref_329; // class=java/lang/StringBuilder, name=append, descriptor=(J)Ljava/lang/StringBuilder;
    wide aload a_393;
    invokevirtual methodref_316; // class=java/lang/StringBuilder, name=append, descriptor=(Ljava/lang/Object;)Ljava/lang/StringBuilder;
    wide fload f_394;
    invokevirtual methodref_320; // class=java/lang/StringBuilder, name=append, descriptor=(F)Ljava/lang/StringBuilder;
    wide dload d_395;
    invokevirtual methodref_323; // class=java/lang/StringBuilder, name=append, descriptor=(D)Ljava/lang/StringBuilder;
    wide iload i_397;
    invokevirtual methodref_326; // class=java/lang/StringBuilder, name=append, descriptor=(I)Ljava/lang/StringBuilder;
    wide lload l_398;
    invokevirtual methodref_329; // class=java/lang/StringBuilder, name=append, descriptor=(J)Ljava/lang/StringBuilder;
    wide aload a_400;
    invokevirtual methodref_316; // class=java/lang/StringBuilder, name=append, descriptor=(Ljava/lang/Object;)Ljava/lang/StringBuilder;
    wide fload f_401;
    invokevirtual methodref_320; // class=java/lang/StringBuilder, name=append, descriptor=(F)Ljava/lang/StringBuilder;
    wide dload d_402;
    invokevirtual methodref_323; // class=java/lang/StringBuilder, name=append, descriptor=(D)Ljava/lang/StringBuilder;
    wide iload i_404;
    invokevirtual methodref_326; // class=java/lang/StringBuilder, name=append, descriptor=(I)Ljava/lang/StringBuilder;
    wide lload l_405;
    invokevirtual methodref_329; // class=java/lang/StringBuilder, name=append, descriptor=(J)Ljava/lang/StringBuilder;
    wide aload a_407;
    invokevirtual methodref_316; // class=java/lang/StringBuilder, name=append, descriptor=(Ljava/lang/Object;)Ljava/lang/StringBuilder;
    wide fload f_408;
    invokevirtual methodref_320; // class=java/lang/StringBuilder, name=append, descriptor=(F)Ljava/lang/StringBuilder;
    wide dload d_409;
    invokevirtual methodref_323; // class=java/lang/StringBuilder, name=append, descriptor=(D)Ljava/lang/StringBuilder;
    wide iload i_411;
    invokevirtual methodref_326; // class=java/lang/StringBuilder, name=append, descriptor=(I)Ljava/lang/StringBuilder;
    wide lload l_412;
    invokevirtual methodref_329; // class=java/lang/StringBuilder, name=append, descriptor=(J)Ljava/lang/StringBuilder;
    wide aload a_414;
    invokevirtual methodref_316; // class=java/lang/StringBuilder, name=append, descriptor=(Ljava/lang/Object;)Ljava/lang/StringBuilder;
    wide fload f_415;
    invokevirtual methodref_320; // class=java/lang/StringBuilder, name=append, descriptor=(F)Ljava/lang/StringBuilder;
    wide dload d_416;
    invokevirtual methodref_323; // class=java/lang/StringBuilder, name=append, descriptor=(D)Ljava/lang/StringBuilder;
    wide iload i_418;
    invokevirtual methodref_326; // class=java/lang/StringBuilder, name=append, descriptor=(I)Ljava/lang/StringBuilder;
    wide lload l_419;
    invokevirtual methodref_329; // class=java/lang/StringBuilder, name=append, descriptor=(J)Ljava/lang/StringBuilder;
    invokevirtual methodref_332; // class=java/lang/StringBuilder, name=toString, descriptor=()Ljava/lang/String;
    wide astore a_421;
    ir3286: return;
  }
  public static method {
    name utf8_643; // main
    descriptor utf8_644; // ([Ljava/lang/String;)V
    line numbers {
      line ir0, 314;
      line ir5, 315;
      line ir11, 316;
      line ir43, 317;
      line ir50, 318;
      line ir92, 319;
      line ir99, 320;
      line ir141, 321;
      line ir148, 322;
      line ir190, 323;
      line ir197, 324;
      line ir236, 314;
      line ir246, 328;
      line ir255, 329;
      line ir263, 330;
      line ir271, 331;
      line ir276, 332;
      line ir284, 333;
      line ir290, 334;
      line ir315, 335;
      line ir322, 336;
      line ir347, 337;
      line ir354, 338;
      line ir379, 339;
      line ir386, 340;
      line ir411, 341;
      line ir418, 342;
      line ir440, 331;
      line ir450, 346;
      line ir458, 347;
      line ir468, 348;
    }
    debug vars {
      var a_0, ir0, utf8_705, utf8_706; // name=args,  descriptor=[Ljava/lang/String;
      var i_1, ir2->ir246, utf8_701, utf8_343; // name=i,  descriptor=I
      var a_1, ir263, utf8_707, utf8_708; // name=buf,  descriptor=Ljava/lang/StringBuffer;
      var i_2, ir273->ir450, utf8_701, utf8_343; // name=i,  descriptor=I
    }
    maxstack 4;
    maxlocals 3;
    //Variables
    var object a_0;
    var int i_1;
    var object a_1 at i_1;
    var int i_2;
    //Instructions
    ir0: iconst_0;
    istore i_1;
    ir2: goto ir239;
    ir5: iload i_1;
    iconst_5;
    irem;
    ifne ir43;
    ir11: getstatic fieldref_645; // class=java/lang/System, name=out, descriptor=Ljava/io/PrintStream;
    new classref_313; // java/lang/StringBuilder
    dup;
    ldc string_651; // "Object o"
    invokespecial methodref_653; // class=java/lang/StringBuilder, name=<init>, descriptor=(Ljava/lang/String;)V
    iload i_1;
    invokevirtual methodref_326; // class=java/lang/StringBuilder, name=append, descriptor=(I)Ljava/lang/StringBuilder;
    ldc string_656; // "=null;"
    invokevirtual methodref_658; // class=java/lang/StringBuilder, name=append, descriptor=(Ljava/lang/String;)Ljava/lang/StringBuilder;
    invokevirtual methodref_332; // class=java/lang/StringBuilder, name=toString, descriptor=()Ljava/lang/String;
    invokevirtual methodref_661; // class=java/io/PrintStream, name=println, descriptor=(Ljava/lang/String;)V
    goto ir236;
    ir43: iload i_1;
    iconst_5;
    irem;
    iconst_1;
    if_icmpne ir92;
    ir50: getstatic fieldref_645; // class=java/lang/System, name=out, descriptor=Ljava/io/PrintStream;
    new classref_313; // java/lang/StringBuilder
    dup;
    ldc string_666; // "float f"
    invokespecial methodref_653; // class=java/lang/StringBuilder, name=<init>, descriptor=(Ljava/lang/String;)V
    iload i_1;
    invokevirtual methodref_326; // class=java/lang/StringBuilder, name=append, descriptor=(I)Ljava/lang/StringBuilder;
    ldc string_668; // "="
    invokevirtual methodref_658; // class=java/lang/StringBuilder, name=append, descriptor=(Ljava/lang/String;)Ljava/lang/StringBuilder;
    iload i_1;
    invokevirtual methodref_326; // class=java/lang/StringBuilder, name=append, descriptor=(I)Ljava/lang/StringBuilder;
    ldc string_670; // ".0f;"
    invokevirtual methodref_658; // class=java/lang/StringBuilder, name=append, descriptor=(Ljava/lang/String;)Ljava/lang/StringBuilder;
    invokevirtual methodref_332; // class=java/lang/StringBuilder, name=toString, descriptor=()Ljava/lang/String;
    invokevirtual methodref_661; // class=java/io/PrintStream, name=println, descriptor=(Ljava/lang/String;)V
    goto ir236;
    ir92: iload i_1;
    iconst_5;
    irem;
    iconst_2;
    if_icmpne ir141;
    ir99: getstatic fieldref_645; // class=java/lang/System, name=out, descriptor=Ljava/io/PrintStream;
    new classref_313; // java/lang/StringBuilder
    dup;
    ldc string_672; // "double d"
    invokespecial methodref_653; // class=java/lang/StringBuilder, name=<init>, descriptor=(Ljava/lang/String;)V
    iload i_1;
    invokevirtual methodref_326; // class=java/lang/StringBuilder, name=append, descriptor=(I)Ljava/lang/StringBuilder;
    ldc string_668; // "="
    invokevirtual methodref_658; // class=java/lang/StringBuilder, name=append, descriptor=(Ljava/lang/String;)Ljava/lang/StringBuilder;
    iload i_1;
    invokevirtual methodref_326; // class=java/lang/StringBuilder, name=append, descriptor=(I)Ljava/lang/StringBuilder;
    ldc string_674; // ".0;"
    invokevirtual methodref_658; // class=java/lang/StringBuilder, name=append, descriptor=(Ljava/lang/String;)Ljava/lang/StringBuilder;
    invokevirtual methodref_332; // class=java/lang/StringBuilder, name=toString, descriptor=()Ljava/lang/String;
    invokevirtual methodref_661; // class=java/io/PrintStream, name=println, descriptor=(Ljava/lang/String;)V
    goto ir236;
    ir141: iload i_1;
    iconst_5;
    irem;
    iconst_3;
    if_icmpne ir190;
    ir148: getstatic fieldref_645; // class=java/lang/System, name=out, descriptor=Ljava/io/PrintStream;
    new classref_313; // java/lang/StringBuilder
    dup;
    ldc string_676; // "int i"
    invokespecial methodref_653; // class=java/lang/StringBuilder, name=<init>, descriptor=(Ljava/lang/String;)V
    iload i_1;
    invokevirtual methodref_326; // class=java/lang/StringBuilder, name=append, descriptor=(I)Ljava/lang/StringBuilder;
    ldc string_668; // "="
    invokevirtual methodref_658; // class=java/lang/StringBuilder, name=append, descriptor=(Ljava/lang/String;)Ljava/lang/StringBuilder;
    iload i_1;
    invokevirtual methodref_326; // class=java/lang/StringBuilder, name=append, descriptor=(I)Ljava/lang/StringBuilder;
    ldc string_678; // ";"
    invokevirtual methodref_658; // class=java/lang/StringBuilder, name=append, descriptor=(Ljava/lang/String;)Ljava/lang/StringBuilder;
    invokevirtual methodref_332; // class=java/lang/StringBuilder, name=toString, descriptor=()Ljava/lang/String;
    invokevirtual methodref_661; // class=java/io/PrintStream, name=println, descriptor=(Ljava/lang/String;)V
    goto ir236;
    ir190: iload i_1;
    iconst_5;
    irem;
    iconst_4;
    if_icmpne ir236;
    ir197: getstatic fieldref_645; // class=java/lang/System, name=out, descriptor=Ljava/io/PrintStream;
    new classref_313; // java/lang/StringBuilder
    dup;
    ldc string_680; // "long l"
    invokespecial methodref_653; // class=java/lang/StringBuilder, name=<init>, descriptor=(Ljava/lang/String;)V
    iload i_1;
    invokevirtual methodref_326; // class=java/lang/StringBuilder, name=append, descriptor=(I)Ljava/lang/StringBuilder;
    ldc string_668; // "="
    invokevirtual methodref_658; // class=java/lang/StringBuilder, name=append, descriptor=(Ljava/lang/String;)Ljava/lang/StringBuilder;
    iload i_1;
    invokevirtual methodref_326; // class=java/lang/StringBuilder, name=append, descriptor=(I)Ljava/lang/StringBuilder;
    ldc string_678; // ";"
    invokevirtual methodref_658; // class=java/lang/StringBuilder, name=append, descriptor=(Ljava/lang/String;)Ljava/lang/StringBuilder;
    invokevirtual methodref_332; // class=java/lang/StringBuilder, name=toString, descriptor=()Ljava/lang/String;
    invokevirtual methodref_661; // class=java/io/PrintStream, name=println, descriptor=(Ljava/lang/String;)V
    ir236: iinc i_1, 1;
    ir239: iload i_1;
    sipush 300;
    if_icmplt ir5;
    ir246: getstatic fieldref_645; // class=java/lang/System, name=out, descriptor=Ljava/io/PrintStream;
    ldc string_682; // "String sum;"
    invokevirtual methodref_661; // class=java/io/PrintStream, name=println, descriptor=(Ljava/lang/String;)V
    ir255: new classref_684; // java/lang/StringBuffer
    dup;
    invokespecial methodref_686; // class=java/lang/StringBuffer, name=<init>, descriptor=()V
    astore a_1;
    ir263: aload a_1;
    ldc string_687; // "sum=\"\""
    invokevirtual methodref_689; // class=java/lang/StringBuffer, name=append, descriptor=(Ljava/lang/String;)Ljava/lang/StringBuffer;
    pop;
    ir271: iconst_0;
    istore i_2;
    ir273: goto ir443;
    ir276: aload a_1;
    ldc string_692; // "+"
    invokevirtual methodref_689; // class=java/lang/StringBuffer, name=append, descriptor=(Ljava/lang/String;)Ljava/lang/StringBuffer;
    pop;
    ir284: iload i_2;
    iconst_5;
    irem;
    ifne ir315;
    ir290: aload a_1;
    new classref_313; // java/lang/StringBuilder
    dup;
    ldc string_694; // "o"
    invokespecial methodref_653; // class=java/lang/StringBuilder, name=<init>, descriptor=(Ljava/lang/String;)V
    iload i_2;
    invokevirtual methodref_326; // class=java/lang/StringBuilder, name=append, descriptor=(I)Ljava/lang/StringBuilder;
    invokevirtual methodref_332; // class=java/lang/StringBuilder, name=toString, descriptor=()Ljava/lang/String;
    invokevirtual methodref_689; // class=java/lang/StringBuffer, name=append, descriptor=(Ljava/lang/String;)Ljava/lang/StringBuffer;
    pop;
    goto ir440;
    ir315: iload i_2;
    iconst_5;
    irem;
    iconst_1;
    if_icmpne ir347;
    ir322: aload a_1;
    new classref_313; // java/lang/StringBuilder
    dup;
    ldc string_696; // "f"
    invokespecial methodref_653; // class=java/lang/StringBuilder, name=<init>, descriptor=(Ljava/lang/String;)V
    iload i_2;
    invokevirtual methodref_326; // class=java/lang/StringBuilder, name=append, descriptor=(I)Ljava/lang/StringBuilder;
    invokevirtual methodref_332; // class=java/lang/StringBuilder, name=toString, descriptor=()Ljava/lang/String;
    invokevirtual methodref_689; // class=java/lang/StringBuffer, name=append, descriptor=(Ljava/lang/String;)Ljava/lang/StringBuffer;
    pop;
    goto ir440;
    ir347: iload i_2;
    iconst_5;
    irem;
    iconst_2;
    if_icmpne ir379;
    ir354: aload a_1;
    new classref_313; // java/lang/StringBuilder
    dup;
    ldc string_698; // "d"
    invokespecial methodref_653; // class=java/lang/StringBuilder, name=<init>, descriptor=(Ljava/lang/String;)V
    iload i_2;
    invokevirtual methodref_326; // class=java/lang/StringBuilder, name=append, descriptor=(I)Ljava/lang/StringBuilder;
    invokevirtual methodref_332; // class=java/lang/StringBuilder, name=toString, descriptor=()Ljava/lang/String;
    invokevirtual methodref_689; // class=java/lang/StringBuffer, name=append, descriptor=(Ljava/lang/String;)Ljava/lang/StringBuffer;
    pop;
    goto ir440;
    ir379: iload i_2;
    iconst_5;
    irem;
    iconst_3;
    if_icmpne ir411;
    ir386: aload a_1;
    new classref_313; // java/lang/StringBuilder
    dup;
    ldc string_700; // "i"
    invokespecial methodref_653; // class=java/lang/StringBuilder, name=<init>, descriptor=(Ljava/lang/String;)V
    iload i_2;
    invokevirtual methodref_326; // class=java/lang/StringBuilder, name=append, descriptor=(I)Ljava/lang/StringBuilder;
    invokevirtual methodref_332; // class=java/lang/StringBuilder, name=toString, descriptor=()Ljava/lang/String;
    invokevirtual methodref_689; // class=java/lang/StringBuffer, name=append, descriptor=(Ljava/lang/String;)Ljava/lang/StringBuffer;
    pop;
    goto ir440;
    ir411: iload i_2;
    iconst_5;
    irem;
    iconst_4;
    if_icmpne ir440;
    ir418: aload a_1;
    new classref_313; // java/lang/StringBuilder
    dup;
    ldc string_702; // "l"
    invokespecial methodref_653; // class=java/lang/StringBuilder, name=<init>, descriptor=(Ljava/lang/String;)V
    iload i_2;
    invokevirtual methodref_326; // class=java/lang/StringBuilder, name=append, descriptor=(I)Ljava/lang/StringBuilder;
    invokevirtual methodref_332; // class=java/lang/StringBuilder, name=toString, descriptor=()Ljava/lang/String;
    invokevirtual methodref_689; // class=java/lang/StringBuffer, name=append, descriptor=(Ljava/lang/String;)Ljava/lang/StringBuffer;
    pop;
    ir440: iinc i_2, 1;
    ir443: iload i_2;
    sipush 300;
    if_icmplt ir276;
    ir450: aload a_1;
    ldc string_678; // ";"
    invokevirtual methodref_689; // class=java/lang/StringBuffer, name=append, descriptor=(Ljava/lang/String;)Ljava/lang/StringBuffer;
    pop;
    ir458: getstatic fieldref_645; // class=java/lang/System, name=out, descriptor=Ljava/io/PrintStream;
    aload a_1;
    invokevirtual methodref_704; // class=java/lang/StringBuffer, name=toString, descriptor=()Ljava/lang/String;
    invokevirtual methodref_661; // class=java/io/PrintStream, name=println, descriptor=(Ljava/lang/String;)V
    ir468: return;
  }
}